{"fftArray":[{"fileName":"chuangzhonghei.ttf","url":"https:\/\/fb-cdn.fanbook.mobi\/fanbook\/meishe\/SDKLib\/font\/chuangzhonghei.ttf","strong":0,"md5":"f95f6320de15f342fae0e4fe43f39e0b","image":"https:\/\/fb-cdn.fanbook.mobi\/fanbook\/meishe\/SDKLib\/font\/chuangzhonghei.png","name":"chuangzhonghei"},{"fileName":"ExtraBold.ttf","url":"https:\/\/fb-cdn.fanbook.mobi\/fanbook\/meishe\/SDKLib\/font\/ExtraBold.ttf","strong":0,"md5":"0bce91404ac6ed923ccd48644d687df2","image":"https:\/\/fb-cdn.fanbook.mobi\/fanbook\/meishe\/SDKLib\/font\/ExtraBold.png","name":"ExtraBold"},{"fileName":"shrikhand.ttf","url":"https:\/\/fb-cdn.fanbook.mobi\/fanbook\/meishe\/SDKLib\/font\/shrikhand.ttf","strong":0,"md5":"b2142f626983b4a663cb43a84f2e086d","image":"https:\/\/fb-cdn.fanbook.mobi\/fanbook\/meishe\/SDKLib\/font\/shrikhand.png","name":"shrikhand"},{"fileName":"zihun.ttf","url":"https:\/\/fb-cdn.fanbook.mobi\/fanbook\/meishe\/SDKLib\/font\/zihun.ttf","strong":0,"md5":"64258f0318fffb67dee8c867f7feb0ea","image":"https:\/\/fb-cdn.fanbook.mobi\/fanbook\/meishe\/SDKLib\/font\/zihun.png","name":"zihun"},{"fileName":"chuangchuhei.ttf","url":"https:\/\/fb-cdn.fanbook.mobi\/fanbook\/meishe\/SDKLib\/font\/chuangchuhei.ttf","strong":0,"md5":"3e1cdf4d1634e5cf88aaef233ca1faa6","image":"https:\/\/fb-cdn.fanbook.mobi\/fanbook\/meishe\/SDKLib\/font\/chuangchuhei.png","name":"chuangchuhei"},{"fileName":"wangchaoti.ttf","url":"https:\/\/fb-cdn.fanbook.mobi\/fanbook\/meishe\/SDKLib\/font\/wangchaoti.ttf","strong":0,"md5":"d51f1d763f1f68f9cb04e02e4a4f89c5","image":"https:\/\/fb-cdn.fanbook.mobi\/fanbook\/meishe\/SDKLib\/font\/wangchaoti.png","name":"wangchaoti"},{"fileName":"zhongming.ttf","url":"https:\/\/fb-cdn.fanbook.mobi\/fanbook\/meishe\/SDKLib\/font\/zhongming.ttf","strong":0,"md5":"01fbc81ed9c6e36008987178a7c30986","image":"https:\/\/fb-cdn.fanbook.mobi\/fanbook\/meishe\/SDKLib\/font\/zhongming.png","name":"zhongming"},{"fileName":"yinghuashaonv.ttf","url":"https:\/\/fb-cdn.fanbook.mobi\/fanbook\/meishe\/SDKLib\/font\/yinghuashaonv.ttf","strong":0,"md5":"302a295a88bb441daa0c10308fb53abc","image":"https:\/\/fb-cdn.fanbook.mobi\/fanbook\/meishe\/SDKLib\/font\/yinghuashaonv.png","name":"yinghuashaonv"},{"fileName":"Lobster.ttf","url":"https:\/\/fb-cdn.fanbook.mobi\/fanbook\/meishe\/SDKLib\/font\/Lobster.ttf","strong":0,"md5":"c3191f3b933ae0bd46335e178744326e","image":"https:\/\/fb-cdn.fanbook.mobi\/fanbook\/meishe\/SDKLib\/font\/Lobster.png","name":"Lobster"},{"fileName":"yahei.ttf","url":"https:\/\/fb-cdn.fanbook.mobi\/fanbook\/meishe\/SDKLib\/font\/yahei.ttf","strong":0,"md5":"540041bb4729e4dfb8a2b8b1a1311e86","image":"https:\/\/fb-cdn.fanbook.mobi\/fanbook\/meishe\/SDKLib\/font\/yahei.png","name":"yahei"},{"fileName":"xinghan.ttf","url":"https:\/\/fb-cdn.fanbook.mobi\/fanbook\/meishe\/SDKLib\/font\/xinghan.ttf","strong":0,"md5":"d90cbf44d29c49b881be01fb43a838dd","image":"https:\/\/fb-cdn.fanbook.mobi\/fanbook\/meishe\/SDKLib\/font\/xinghan.png","name":"xinghan"},{"fileName":"yingxionghei.ttf","url":"https:\/\/fb-cdn.fanbook.mobi\/fanbook\/meishe\/SDKLib\/font\/yingxionghei.ttf","strong":0,"md5":"b535d9b84ef3429b39b0f3e846d73c9e","image":"https:\/\/fb-cdn.fanbook.mobi\/fanbook\/meishe\/SDKLib\/font\/yingxionghei.png","name":"yingxionghei"},{"fileName":"feichi.ttf","url":"https:\/\/fb-cdn.fanbook.mobi\/fanbook\/meishe\/SDKLib\/font\/feichi.ttf","strong":0,"md5":"829965ff0b432af4bbbb85cae1ef0dce","image":"https:\/\/fb-cdn.fanbook.mobi\/fanbook\/meishe\/SDKLib\/font\/feichi.png","name":"feichi"},{"fileName":"bingyuyasong.ttf","url":"https:\/\/fb-cdn.fanbook.mobi\/fanbook\/meishe\/SDKLib\/font\/bingyuyasong.ttf","strong":0,"md5":"a2a9c7a516c01779194ecc0526f2ff53","image":"https:\/\/fb-cdn.fanbook.mobi\/fanbook\/meishe\/SDKLib\/font\/bingyuyasong.png","name":"bingyuyasong"},{"fileName":"Josefin_Slab.ttf","url":"https:\/\/fb-cdn.fanbook.mobi\/fanbook\/meishe\/SDKLib\/font\/Josefin_Slab.ttf","strong":0,"md5":"3f3433df3d637462012f9ef94900635d","image":"https:\/\/fb-cdn.fanbook.mobi\/fanbook\/meishe\/SDKLib\/font\/Josefin_Slab.png","name":"Josefin Slab"},{"fileName":"SIGMAR.ttf","url":"https:\/\/fb-cdn.fanbook.mobi\/fanbook\/meishe\/SDKLib\/font\/SIGMAR.ttf","strong":0,"md5":"9a721a3ad1f6ddd908c1a369b75a12cd","image":"https:\/\/fb-cdn.fanbook.mobi\/fanbook\/meishe\/SDKLib\/font\/SIGMAR.png","name":"SIGMAR"},{"fileName":"Modak.ttf","url":"https:\/\/fb-cdn.fanbook.mobi\/fanbook\/meishe\/SDKLib\/font\/Modak.ttf","strong":0,"md5":"9b6bdd2608ad69f1e4f379fadcd6aec5","image":"https:\/\/fb-cdn.fanbook.mobi\/fanbook\/meishe\/SDKLib\/font\/Modak.png","name":"Modak"},{"fileName":"Frank.ttf","url":"https:\/\/fb-cdn.fanbook.mobi\/fanbook\/meishe\/SDKLib\/font\/Frank.ttf","strong":0,"md5":"bff507323e3c7a15fddb58f466e6a6e9","image":"https:\/\/fb-cdn.fanbook.mobi\/fanbook\/meishe\/SDKLib\/font\/Frank.png","name":"Frank"},{"fileName":"Sans.ttf","url":"https:\/\/fb-cdn.fanbook.mobi\/fanbook\/meishe\/SDKLib\/font\/Sans.ttf","strong":0,"md5":"b5c77a6aed75cdad9489effd0d5ea411","image":"https:\/\/fb-cdn.fanbook.mobi\/fanbook\/meishe\/SDKLib\/font\/Sans.png","name":"Sans"},{"fileName":"Josefin.ttf","url":"https:\/\/fb-cdn.fanbook.mobi\/fanbook\/meishe\/SDKLib\/font\/Josefin.ttf","strong":0,"md5":"36699ca6fe30d1ff7a718f0655653374","image":"https:\/\/fb-cdn.fanbook.mobi\/fanbook\/meishe\/SDKLib\/font\/Josefin.png","name":"Josefin"}],"captionArray":[{"fileName":"F033B550-80FF-4115-B734-D99E44A71507.2.captionstyle","url":"https:\/\/fb-cdn.fanbook.mobi\/fanbook\/meishe\/SDKLib\/captionSource2\/F033B550-80FF-4115-B734-D99E44A71507.2.captionstyle","strong":0,"md5":"010805d06f74f18208361369994fc1cc","image":"https:\/\/fb-cdn.fanbook.mobi\/fanbook\/meishe\/SDKLib\/captionSource2\/F033B550-80FF-4115-B734-D99E44A71507.png","name":"日历","zip":"https:\/\/fb-cdn.fanbook.mobi\/fanbook\/meishe\/SDKLib\/captionSource2\/F033B550-80FF-4115-B734-D99E44A71507.zip","lic":"https:\/\/fb-cdn.fanbook.mobi\/fanbook\/meishe\/SDKLib\/caption\/1-日历\/F033B550-80FF-4115-B734-D99E44A71507.lic"},{"fileName":"AC15DF60-47E9-45BF-AD8C-A9F33064888F.3.captionstyle","url":"https:\/\/fb-cdn.fanbook.mobi\/fanbook\/meishe\/SDKLib\/fix\/AC15DF60-47E9-45BF-AD8C-A9F33064888F.3.captionstyle","strong":0,"md5":"c050d63e23f8c1476db545f31f46fdb5","image":"https:\/\/fb-cdn.fanbook.mobi\/fanbook\/meishe\/SDKLib\/captionSource2\/AC15DF60-47E9-45BF-AD8C-A9F33064888F.png","name":"地点","zip":"https:\/\/fb-cdn.fanbook.mobi\/fanbook\/meishe\/SDKLib\/fix\/AC15DF60-47E9-45BF-AD8C-A9F33064888F.zip","lic":"https:\/\/fb-cdn.fanbook.mobi\/fanbook\/meishe\/SDKLib\/caption\/2-地点\/AC15DF60-47E9-45BF-AD8C-A9F33064888F.lic"},{"fileName":"E8FD3867-4A6A-4A7E-9F9D-55C1A1AFA27F.1.captionstyle","url":"https:\/\/fb-cdn.fanbook.mobi\/fanbook\/meishe\/SDKLib\/captionSource2\/E8FD3867-4A6A-4A7E-9F9D-55C1A1AFA27F.1.captionstyle","strong":0,"md5":"7f4fba69db0919b1c8c75842c61ca454","image":"https:\/\/fb-cdn.fanbook.mobi\/fanbook\/meishe\/SDKLib\/captionSource2\/E8FD3867-4A6A-4A7E-9F9D-55C1A1AFA27F.webp","name":"春日","zip":"https:\/\/fb-cdn.fanbook.mobi\/fanbook\/meishe\/SDKLib\/captionSource2\/E8FD3867-4A6A-4A7E-9F9D-55C1A1AFA27F.zip","lic":"https:\/\/fb-cdn.fanbook.mobi\/fanbook\/meishe\/SDKLib\/caption\/3-春日\/E8FD3867-4A6A-4A7E-9F9D-55C1A1AFA27F.lic"},{"fileName":"7ADEFB24-CF15-4851-AA58-A9AC7DC01751.4.captionstyle","url":"https:\/\/fb-cdn.fanbook.mobi\/fanbook\/meishe\/SDKLib\/captionSource2\/7ADEFB24-CF15-4851-AA58-A9AC7DC01751.4.captionstyle","strong":0,"md5":"58a0f62606498a30937995d669e0d301","image":"https:\/\/fb-cdn.fanbook.mobi\/fanbook\/meishe\/SDKLib\/captionSource2\/7ADEFB24-CF15-4851-AA58-A9AC7DC01751.png","name":"微信绿","zip":"https:\/\/fb-cdn.fanbook.mobi\/fanbook\/meishe\/SDKLib\/captionSource2\/7ADEFB24-CF15-4851-AA58-A9AC7DC01751.zip","lic":"https:\/\/fb-cdn.fanbook.mobi\/fanbook\/meishe\/SDKLib\/caption\/4-微信绿\/7ADEFB24-CF15-4851-AA58-A9AC7DC01751.lic"},{"fileName":"64CC2CAC-174E-4BCC-9013-34B550744DEA.4.captionstyle","url":"https:\/\/fb-cdn.fanbook.mobi\/fanbook\/meishe\/SDKLib\/captionSource2\/64CC2CAC-174E-4BCC-9013-34B550744DEA.4.captionstyle","strong":0,"md5":"93e52a4ffadc868b804a6e0e8e858feb","image":"https:\/\/fb-cdn.fanbook.mobi\/fanbook\/meishe\/SDKLib\/captionSource2\/64CC2CAC-174E-4BCC-9013-34B550744DEA.png","name":"云白","zip":"https:\/\/fb-cdn.fanbook.mobi\/fanbook\/meishe\/SDKLib\/captionSource2\/64CC2CAC-174E-4BCC-9013-34B550744DEA.zip","lic":"https:\/\/fb-cdn.fanbook.mobi\/fanbook\/meishe\/SDKLib\/caption\/5-云白\/64CC2CAC-174E-4BCC-9013-34B550744DEA.lic"},{"fileName":"68E6BA38-17C0-4B6B-9653-CE5351A070DF.1.captionstyle","url":"https:\/\/fb-cdn.fanbook.mobi\/fanbook\/meishe\/SDKLib\/captionSource2\/68E6BA38-17C0-4B6B-9653-CE5351A070DF.1.captionstyle","strong":0,"md5":"c94b78f51ef96c77a331fdf43762ec86","image":"https:\/\/fb-cdn.fanbook.mobi\/fanbook\/meishe\/SDKLib\/captionSource2\/68E6BA38-17C0-4B6B-9653-CE5351A070DF.png","name":"抹茶奶霜","zip":"https:\/\/fb-cdn.fanbook.mobi\/fanbook\/meishe\/SDKLib\/captionSource2\/68E6BA38-17C0-4B6B-9653-CE5351A070DF.zip","lic":"https:\/\/fb-cdn.fanbook.mobi\/fanbook\/meishe\/SDKLib\/caption\/6-抹茶奶霜\/68E6BA38-17C0-4B6B-9653-CE5351A070DF.lic"},{"fileName":"331BCA93-6CA0-4C01-AA2D-479A8EC28E3E.1.captionstyle","url":"https:\/\/fb-cdn.fanbook.mobi\/fanbook\/meishe\/SDKLib\/captionSource2\/331BCA93-6CA0-4C01-AA2D-479A8EC28E3E.1.captionstyle","strong":0,"md5":"acae56c494daa16696e036de585a82d5","image":"https:\/\/fb-cdn.fanbook.mobi\/fanbook\/meishe\/SDKLib\/captionSource2\/331BCA93-6CA0-4C01-AA2D-479A8EC28E3E.png","name":"好物种草","zip":"https:\/\/fb-cdn.fanbook.mobi\/fanbook\/meishe\/SDKLib\/captionSource2\/331BCA93-6CA0-4C01-AA2D-479A8EC28E3E.zip","lic":"https:\/\/fb-cdn.fanbook.mobi\/fanbook\/meishe\/SDKLib\/caption\/7-好物种草\/331BCA93-6CA0-4C01-AA2D-479A8EC28E3E.lic"},{"fileName":"EFB0DAF7-DA5F-459E-AECA-7C9697A0145E.2.captionstyle","url":"https:\/\/fb-cdn.fanbook.mobi\/fanbook\/meishe\/SDKLib\/captionSource2\/EFB0DAF7-DA5F-459E-AECA-7C9697A0145E.2.captionstyle","strong":0,"md5":"7d2df094b35b3dd16063eb7c497acdfc","image":"https:\/\/fb-cdn.fanbook.mobi\/fanbook\/meishe\/SDKLib\/captionSource2\/EFB0DAF7-DA5F-459E-AECA-7C9697A0145E.png","name":"忙于快乐","zip":"https:\/\/fb-cdn.fanbook.mobi\/fanbook\/meishe\/SDKLib\/captionSource2\/EFB0DAF7-DA5F-459E-AECA-7C9697A0145E.zip","lic":"https:\/\/fb-cdn.fanbook.mobi\/fanbook\/meishe\/SDKLib\/caption\/8-忙于快乐\/EFB0DAF7-DA5F-459E-AECA-7C9697A0145E.lic"},{"fileName":"DE7758B3-107F-43A8-9BE6-5402FABDB65C.2.captionstyle","url":"https:\/\/fb-cdn.fanbook.mobi\/fanbook\/meishe\/SDKLib\/captionSource2\/DE7758B3-107F-43A8-9BE6-5402FABDB65C.2.captionstyle","strong":0,"md5":"a99ea44d57ca7eb9662e66f6fd8e8664","image":"https:\/\/fb-cdn.fanbook.mobi\/fanbook\/meishe\/SDKLib\/captionSource2\/DE7758B3-107F-43A8-9BE6-5402FABDB65C.png","name":"今日打卡","zip":"https:\/\/fb-cdn.fanbook.mobi\/fanbook\/meishe\/SDKLib\/captionSource2\/DE7758B3-107F-43A8-9BE6-5402FABDB65C.zip","lic":"https:\/\/fb-cdn.fanbook.mobi\/fanbook\/meishe\/SDKLib\/caption\/9-今日打卡\/DE7758B3-107F-43A8-9BE6-5402FABDB65C.lic"},{"fileName":"07910416-ECEC-47D7-BC85-08C6C2BAFE89.1.captionstyle","url":"https:\/\/fb-cdn.fanbook.mobi\/fanbook\/meishe\/SDKLib\/captionSource2\/07910416-ECEC-47D7-BC85-08C6C2BAFE89.1.captionstyle","strong":0,"md5":"e784586aad199ed3b821b35ba68cca03","image":"https:\/\/fb-cdn.fanbook.mobi\/fanbook\/meishe\/SDKLib\/captionSource2\/07910416-ECEC-47D7-BC85-08C6C2BAFE89.png","name":"好运锦鲤","zip":"https:\/\/fb-cdn.fanbook.mobi\/fanbook\/meishe\/SDKLib\/captionSource2\/07910416-ECEC-47D7-BC85-08C6C2BAFE89.zip","lic":"https:\/\/fb-cdn.fanbook.mobi\/fanbook\/meishe\/SDKLib\/caption\/10-好运锦鲤\/07910416-ECEC-47D7-BC85-08C6C2BAFE89.lic"},{"fileName":"71B5163D-5CA3-4821-B9C4-BE7DC2EEAC36.1.captionstyle","url":"https:\/\/fb-cdn.fanbook.mobi\/fanbook\/meishe\/SDKLib\/captionSource2\/71B5163D-5CA3-4821-B9C4-BE7DC2EEAC36.1.captionstyle","strong":0,"md5":"516ee601a4025cae46182d487e00de6c","image":"https:\/\/fb-cdn.fanbook.mobi\/fanbook\/meishe\/SDKLib\/captionSource2\/71B5163D-5CA3-4821-B9C4-BE7DC2EEAC36.png","name":"彩虹小心心","zip":"https:\/\/fb-cdn.fanbook.mobi\/fanbook\/meishe\/SDKLib\/captionSource2\/71B5163D-5CA3-4821-B9C4-BE7DC2EEAC36.zip","lic":"https:\/\/fb-cdn.fanbook.mobi\/fanbook\/meishe\/SDKLib\/caption\/11-彩虹小心心\/71B5163D-5CA3-4821-B9C4-BE7DC2EEAC36.lic"},{"fileName":"011D788D-DA83-43C4-88E9-2A176C7DE5A9.2.captionstyle","url":"https:\/\/fb-cdn.fanbook.mobi\/fanbook\/meishe\/SDKLib\/captionSource2\/011D788D-DA83-43C4-88E9-2A176C7DE5A9.2.captionstyle","strong":0,"md5":"d14b37da093227e2d70d610a3cea179a","image":"https:\/\/fb-cdn.fanbook.mobi\/fanbook\/meishe\/SDKLib\/captionSource2\/011D788D-DA83-43C4-88E9-2A176C7DE5A9.png","name":"彩虹独角兽","zip":"https:\/\/fb-cdn.fanbook.mobi\/fanbook\/meishe\/SDKLib\/captionSource2\/011D788D-DA83-43C4-88E9-2A176C7DE5A9.zip","lic":"https:\/\/fb-cdn.fanbook.mobi\/fanbook\/meishe\/SDKLib\/caption\/12-彩虹独角兽\/011D788D-DA83-43C4-88E9-2A176C7DE5A9.lic"},{"fileName":"3396C431-3AEB-42FA-B9C3-74F01A7A2D34.1.captionstyle","url":"https:\/\/fb-cdn.fanbook.mobi\/fanbook\/meishe\/SDKLib\/captionSource2\/3396C431-3AEB-42FA-B9C3-74F01A7A2D34.1.captionstyle","strong":0,"md5":"b51683b0a3f1b1b7025cfe3bc443df8b","image":"https:\/\/fb-cdn.fanbook.mobi\/fanbook\/meishe\/SDKLib\/captionSource2\/3396C431-3AEB-42FA-B9C3-74F01A7A2D34.png","name":"箭头1","zip":"https:\/\/fb-cdn.fanbook.mobi\/fanbook\/meishe\/SDKLib\/captionSource2\/3396C431-3AEB-42FA-B9C3-74F01A7A2D34.zip","lic":"https:\/\/fb-cdn.fanbook.mobi\/fanbook\/meishe\/SDKLib\/caption\/13-箭头1\/3396C431-3AEB-42FA-B9C3-74F01A7A2D34.lic"},{"fileName":"F4519491-B15C-43A0-BA88-A870DFC20EAB.1.captionstyle","url":"https:\/\/fb-cdn.fanbook.mobi\/fanbook\/meishe\/SDKLib\/captionSource2\/F4519491-B15C-43A0-BA88-A870DFC20EAB.1.captionstyle","strong":0,"md5":"5488859f48d857c32ae978471fb8384c","image":"https:\/\/fb-cdn.fanbook.mobi\/fanbook\/meishe\/SDKLib\/captionSource2\/F4519491-B15C-43A0-BA88-A870DFC20EAB.png","name":"箭头2","zip":"https:\/\/fb-cdn.fanbook.mobi\/fanbook\/meishe\/SDKLib\/captionSource2\/F4519491-B15C-43A0-BA88-A870DFC20EAB.zip","lic":"https:\/\/fb-cdn.fanbook.mobi\/fanbook\/meishe\/SDKLib\/caption\/14-箭头2\/F4519491-B15C-43A0-BA88-A870DFC20EAB.lic"},{"fileName":"D4A1EA61-C1A6-4389-ACC4-3B52F98CD5C0.1.captionstyle","url":"https:\/\/fb-cdn.fanbook.mobi\/fanbook\/meishe\/SDKLib\/captionSource2\/D4A1EA61-C1A6-4389-ACC4-3B52F98CD5C0.1.captionstyle","strong":0,"md5":"0075b55ca6e9f9ffa5ef312ed0eb5c50","image":"https:\/\/fb-cdn.fanbook.mobi\/fanbook\/meishe\/SDKLib\/captionSource2\/D4A1EA61-C1A6-4389-ACC4-3B52F98CD5C0.png","name":"箭头3","zip":"https:\/\/fb-cdn.fanbook.mobi\/fanbook\/meishe\/SDKLib\/captionSource2\/D4A1EA61-C1A6-4389-ACC4-3B52F98CD5C0.zip","lic":"https:\/\/fb-cdn.fanbook.mobi\/fanbook\/meishe\/SDKLib\/caption\/15-箭头3\/D4A1EA61-C1A6-4389-ACC4-3B52F98CD5C0.lic"},{"fileName":"40D86D25-388D-4CCF-A010-989C79C80585.1.captionstyle","url":"https:\/\/fb-cdn.fanbook.mobi\/fanbook\/meishe\/SDKLib\/captionSource2\/40D86D25-388D-4CCF-A010-989C79C80585.1.captionstyle","strong":0,"md5":"4e91301385425dc29e72a6b7e912fa17","image":"https:\/\/fb-cdn.fanbook.mobi\/fanbook\/meishe\/SDKLib\/captionSource2\/40D86D25-388D-4CCF-A010-989C79C80585.png","name":"箭头4","zip":"https:\/\/fb-cdn.fanbook.mobi\/fanbook\/meishe\/SDKLib\/captionSource2\/40D86D25-388D-4CCF-A010-989C79C80585.zip","lic":"https:\/\/fb-cdn.fanbook.mobi\/fanbook\/meishe\/SDKLib\/caption\/16-箭头4\/40D86D25-388D-4CCF-A010-989C79C80585.lic"},{"fileName":"6722F916-ED64-4FD7-8841-2821A48EECE1.7.captionstyle","url":"https:\/\/fb-cdn.fanbook.mobi\/fanbook\/meishe\/SDKLib\/captionSource2\/6722F916-ED64-4FD7-8841-2821A48EECE1.7.captionstyle","strong":0,"md5":"2c65d661bd15c58f64e2197c56021b0f","image":"https:\/\/fb-cdn.fanbook.mobi\/fanbook\/meishe\/SDKLib\/captionSource2\/6722F916-ED64-4FD7-8841-2821A48EECE1.webp","name":"新闻联播","zip":"https:\/\/fb-cdn.fanbook.mobi\/fanbook\/meishe\/SDKLib\/captionSource2\/6722F916-ED64-4FD7-8841-2821A48EECE1.zip","lic":"https:\/\/fb-cdn.fanbook.mobi\/fanbook\/meishe\/SDKLib\/caption\/17-新闻联播\/6722F916-ED64-4FD7-8841-2821A48EECE1.lic"},{"fileName":"C0561830-CA15-4BB9-8827-99A8C86549FE.1.captionstyle","url":"https:\/\/fb-cdn.fanbook.mobi\/fanbook\/meishe\/SDKLib\/captionSource2\/C0561830-CA15-4BB9-8827-99A8C86549FE.1.captionstyle","strong":0,"md5":"b9e577dd0bbaf9bfc64000acf9b5f4c3","image":"https:\/\/fb-cdn.fanbook.mobi\/fanbook\/meishe\/SDKLib\/captionSource2\/C0561830-CA15-4BB9-8827-99A8C86549FE.png","name":"漫画气泡","zip":"https:\/\/fb-cdn.fanbook.mobi\/fanbook\/meishe\/SDKLib\/captionSource2\/C0561830-CA15-4BB9-8827-99A8C86549FE.zip","lic":"https:\/\/fb-cdn.fanbook.mobi\/fanbook\/meishe\/SDKLib\/caption\/19-漫画气泡\/C0561830-CA15-4BB9-8827-99A8C86549FE.lic"},{"fileName":"177DF4EA-291A-4351-B1CF-3789C01D7B35.1.captionstyle","url":"https:\/\/fb-cdn.fanbook.mobi\/fanbook\/meishe\/SDKLib\/captionSource2\/177DF4EA-291A-4351-B1CF-3789C01D7B35.1.captionstyle","strong":0,"md5":"62be09310c213666026eacbed2ceed3c","image":"https:\/\/fb-cdn.fanbook.mobi\/fanbook\/meishe\/SDKLib\/captionSource2\/177DF4EA-291A-4351-B1CF-3789C01D7B35.png","name":"漫画气泡2","zip":"https:\/\/fb-cdn.fanbook.mobi\/fanbook\/meishe\/SDKLib\/captionSource2\/177DF4EA-291A-4351-B1CF-3789C01D7B35.zip","lic":"https:\/\/fb-cdn.fanbook.mobi\/fanbook\/meishe\/SDKLib\/caption\/20-漫画气泡2\/177DF4EA-291A-4351-B1CF-3789C01D7B35.lic"},{"fileName":"146470DB-C2E6-4BBC-9F13-1C7F2FAA1665.1.captionstyle","url":"https:\/\/fb-cdn.fanbook.mobi\/fanbook\/meishe\/SDKLib\/captionSource2\/146470DB-C2E6-4BBC-9F13-1C7F2FAA1665.1.captionstyle","strong":0,"md5":"f9cb8ef0856cea159a25215ed490c51e","image":"https:\/\/fb-cdn.fanbook.mobi\/fanbook\/meishe\/SDKLib\/captionSource2\/146470DB-C2E6-4BBC-9F13-1C7F2FAA1665.png","name":"漫画气泡3","zip":"https:\/\/fb-cdn.fanbook.mobi\/fanbook\/meishe\/SDKLib\/captionSource2\/146470DB-C2E6-4BBC-9F13-1C7F2FAA1665.zip","lic":"https:\/\/fb-cdn.fanbook.mobi\/fanbook\/meishe\/SDKLib\/caption\/21-漫画气泡3\/146470DB-C2E6-4BBC-9F13-1C7F2FAA1665.lic"},{"fileName":"F9A0B435-EA28-4A3F-8A45-F48CA9D8B22A.3.captionstyle","url":"https:\/\/fb-cdn.fanbook.mobi\/fanbook\/meishe\/SDKLib\/captionSource2\/F9A0B435-EA28-4A3F-8A45-F48CA9D8B22A.3.captionstyle","strong":0,"md5":"e45c36abd7320fe5ddf87e57b6236283","image":"https:\/\/fb-cdn.fanbook.mobi\/fanbook\/meishe\/SDKLib\/captionSource2\/F9A0B435-EA28-4A3F-8A45-F48CA9D8B22A.png","name":"福字","zip":"https:\/\/fb-cdn.fanbook.mobi\/fanbook\/meishe\/SDKLib\/captionSource2\/F9A0B435-EA28-4A3F-8A45-F48CA9D8B22A.zip","lic":"https:\/\/fb-cdn.fanbook.mobi\/fanbook\/meishe\/SDKLib\/caption\/22-福字\/F9A0B435-EA28-4A3F-8A45-F48CA9D8B22A.lic"},{"fileName":"E17C48A5-B9A3-4A64-AC85-C19D11365254.3.captionstyle","url":"https:\/\/fb-cdn.fanbook.mobi\/fanbook\/meishe\/SDKLib\/captionSource2\/E17C48A5-B9A3-4A64-AC85-C19D11365254.3.captionstyle","strong":0,"md5":"574375e375c94567afdc67d3d17477e5","image":"https:\/\/fb-cdn.fanbook.mobi\/fanbook\/meishe\/SDKLib\/captionSource2\/E17C48A5-B9A3-4A64-AC85-C19D11365254.png","name":"福字2","zip":"https:\/\/fb-cdn.fanbook.mobi\/fanbook\/meishe\/SDKLib\/captionSource2\/E17C48A5-B9A3-4A64-AC85-C19D11365254.zip","lic":"https:\/\/fb-cdn.fanbook.mobi\/fanbook\/meishe\/SDKLib\/caption\/23-福字2\/E17C48A5-B9A3-4A64-AC85-C19D11365254.lic"},{"fileName":"F0615825-A6D3-482A-82F7-7D82F0EDE9DD.3.captionstyle","url":"https:\/\/fb-cdn.fanbook.mobi\/fanbook\/meishe\/SDKLib\/captionSource2\/F0615825-A6D3-482A-82F7-7D82F0EDE9DD.3.captionstyle","strong":0,"md5":"e6e5a5879915bf9eb5fa18d85758b259","image":"https:\/\/fb-cdn.fanbook.mobi\/fanbook\/meishe\/SDKLib\/captionSource2\/F0615825-A6D3-482A-82F7-7D82F0EDE9DD.png","name":"春联","zip":"https:\/\/fb-cdn.fanbook.mobi\/fanbook\/meishe\/SDKLib\/captionSource2\/F0615825-A6D3-482A-82F7-7D82F0EDE9DD.zip","lic":"https:\/\/fb-cdn.fanbook.mobi\/fanbook\/meishe\/SDKLib\/caption\/24-春联\/F0615825-A6D3-482A-82F7-7D82F0EDE9DD.lic"},{"fileName":"DA3677B5-439C-478A-AE2B-826B147899A7.4.captionstyle","url":"https:\/\/fb-cdn.fanbook.mobi\/fanbook\/meishe\/SDKLib\/captionSource2\/DA3677B5-439C-478A-AE2B-826B147899A7.4.captionstyle","strong":0,"md5":"3ef4a597e0a33228ad8dfc8044066347","image":"https:\/\/fb-cdn.fanbook.mobi\/fanbook\/meishe\/SDKLib\/captionSource2\/DA3677B5-439C-478A-AE2B-826B147899A7.png","name":"春联2","zip":"https:\/\/fb-cdn.fanbook.mobi\/fanbook\/meishe\/SDKLib\/captionSource2\/DA3677B5-439C-478A-AE2B-826B147899A7.zip","lic":"https:\/\/fb-cdn.fanbook.mobi\/fanbook\/meishe\/SDKLib\/caption\/25-春联2\/DA3677B5-439C-478A-AE2B-826B147899A7.lic"},{"fileName":"D58C14C3-4EB5-4A5E-8697-B74EDAD96D45.1.captionstyle","url":"https:\/\/fb-cdn.fanbook.mobi\/fanbook\/meishe\/SDKLib\/captionSource2\/D58C14C3-4EB5-4A5E-8697-B74EDAD96D45.1.captionstyle","strong":0,"md5":"948bac7b68eb6a2b0e8c5f09b35c7dc6","image":"https:\/\/fb-cdn.fanbook.mobi\/fanbook\/meishe\/SDKLib\/captionSource2\/D58C14C3-4EB5-4A5E-8697-B74EDAD96D45.png","name":"新年大吉","zip":"https:\/\/fb-cdn.fanbook.mobi\/fanbook\/meishe\/SDKLib\/captionSource2\/D58C14C3-4EB5-4A5E-8697-B74EDAD96D45.zip","lic":"https:\/\/fb-cdn.fanbook.mobi\/fanbook\/meishe\/SDKLib\/caption\/26-新年大吉\/D58C14C3-4EB5-4A5E-8697-B74EDAD96D45.lic"}],"stickerArray":[{"fileName":"E9838735-A293-48AE-B71C-59467B494491.1.animatedsticker","url":"https:\/\/fb-cdn.fanbook.mobi\/fanbook\/meishe\/SDKLib\/stickerSource2\/E9838735-A293-48AE-B71C-59467B494491.1.animatedsticker","strong":0,"md5":"0237aa9dbce4fa5cd0c5c6a8c8762336","image":"https:\/\/fb-cdn.fanbook.mobi\/fanbook\/meishe\/SDKLib\/stickerSource2\/E9838735-A293-48AE-B71C-59467B494491.webp","name":"Hello","zip":"https:\/\/fb-cdn.fanbook.mobi\/fanbook\/meishe\/SDKLib\/stickerSource2\/E9838735-A293-48AE-B71C-59467B494491.zip","lic":"https:\/\/fb-cdn.fanbook.mobi\/fanbook\/meishe\/SDKLib\/sticker\/1-Hello\/E9838735-A293-48AE-B71C-59467B494491.lic"},{"fileName":"FF33A617-D682-4DEB-AD15-EBD8EDE61BBA.1.animatedsticker","url":"https:\/\/fb-cdn.fanbook.mobi\/fanbook\/meishe\/SDKLib\/stickerSource2\/FF33A617-D682-4DEB-AD15-EBD8EDE61BBA.1.animatedsticker","strong":0,"md5":"e02c604c4132d32637c25d7ddd158fee","image":"https:\/\/fb-cdn.fanbook.mobi\/fanbook\/meishe\/SDKLib\/stickerSource2\/FF33A617-D682-4DEB-AD15-EBD8EDE61BBA.webp","name":"OMG","zip":"https:\/\/fb-cdn.fanbook.mobi\/fanbook\/meishe\/SDKLib\/stickerSource2\/FF33A617-D682-4DEB-AD15-EBD8EDE61BBA.zip","lic":"https:\/\/fb-cdn.fanbook.mobi\/fanbook\/meishe\/SDKLib\/sticker\/2-OMG\/FF33A617-D682-4DEB-AD15-EBD8EDE61BBA.lic"},{"fileName":"4AE9BBC5-B6BF-40A2-890C-1F1E92E966CB.1.animatedsticker","url":"https:\/\/fb-cdn.fanbook.mobi\/fanbook\/meishe\/SDKLib\/stickerSource2\/4AE9BBC5-B6BF-40A2-890C-1F1E92E966CB.1.animatedsticker","strong":0,"md5":"0efed6f38b07b6e38f9969f70403e974","image":"https:\/\/fb-cdn.fanbook.mobi\/fanbook\/meishe\/SDKLib\/stickerSource2\/4AE9BBC5-B6BF-40A2-890C-1F1E92E966CB.png","name":"WoW","zip":"https:\/\/fb-cdn.fanbook.mobi\/fanbook\/meishe\/SDKLib\/stickerSource2\/4AE9BBC5-B6BF-40A2-890C-1F1E92E966CB.zip","lic":"https:\/\/fb-cdn.fanbook.mobi\/fanbook\/meishe\/SDKLib\/sticker\/3-WoW\/4AE9BBC5-B6BF-40A2-890C-1F1E92E966CB.lic"},{"fileName":"9BADEBDB-2F59-4842-BEEE-DE5E5F88DB96.1.animatedsticker","url":"https:\/\/fb-cdn.fanbook.mobi\/fanbook\/meishe\/SDKLib\/stickerSource2\/9BADEBDB-2F59-4842-BEEE-DE5E5F88DB96.1.animatedsticker","strong":0,"md5":"4afb897adad9d8b3d37d40f9877f725b","image":"https:\/\/fb-cdn.fanbook.mobi\/fanbook\/meishe\/SDKLib\/stickerSource2\/9BADEBDB-2F59-4842-BEEE-DE5E5F88DB96.png","name":"CHEER UP","zip":"https:\/\/fb-cdn.fanbook.mobi\/fanbook\/meishe\/SDKLib\/stickerSource2\/9BADEBDB-2F59-4842-BEEE-DE5E5F88DB96.zip","lic":"https:\/\/fb-cdn.fanbook.mobi\/fanbook\/meishe\/SDKLib\/sticker\/4-CHEER UP\/9BADEBDB-2F59-4842-BEEE-DE5E5F88DB96.lic"},{"fileName":"289EB76F-1400-456F-A671-F61A4C9BFF84.1.animatedsticker","url":"https:\/\/fb-cdn.fanbook.mobi\/fanbook\/meishe\/SDKLib\/stickerSource2\/289EB76F-1400-456F-A671-F61A4C9BFF84.1.animatedsticker","strong":0,"md5":"17d9863c71414d8593ddccab58f5a7a6","image":"https:\/\/fb-cdn.fanbook.mobi\/fanbook\/meishe\/SDKLib\/stickerSource2\/289EB76F-1400-456F-A671-F61A4C9BFF84.png","name":"Hello爱心","zip":"https:\/\/fb-cdn.fanbook.mobi\/fanbook\/meishe\/SDKLib\/stickerSource2\/289EB76F-1400-456F-A671-F61A4C9BFF84.zip","lic":"https:\/\/fb-cdn.fanbook.mobi\/fanbook\/meishe\/SDKLib\/sticker\/5-Hello爱心\/289EB76F-1400-456F-A671-F61A4C9BFF84.lic"},{"fileName":"E098BACE-3559-451F-A276-3A660BD765B3.1.animatedsticker","url":"https:\/\/fb-cdn.fanbook.mobi\/fanbook\/meishe\/SDKLib\/stickerSource2\/E098BACE-3559-451F-A276-3A660BD765B3.1.animatedsticker","strong":0,"md5":"c0b69e27083814f800271e41d2354e4f","image":"https:\/\/fb-cdn.fanbook.mobi\/fanbook\/meishe\/SDKLib\/stickerSource2\/E098BACE-3559-451F-A276-3A660BD765B3.png","name":"菠萝","zip":"https:\/\/fb-cdn.fanbook.mobi\/fanbook\/meishe\/SDKLib\/stickerSource2\/E098BACE-3559-451F-A276-3A660BD765B3.zip","lic":"https:\/\/fb-cdn.fanbook.mobi\/fanbook\/meishe\/SDKLib\/sticker\/6-菠萝\/E098BACE-3559-451F-A276-3A660BD765B3.lic"},{"fileName":"BC955A16-8941-48A4-8B08-5A95C8BE0899.1.animatedsticker","url":"https:\/\/fb-cdn.fanbook.mobi\/fanbook\/meishe\/SDKLib\/stickerSource2\/BC955A16-8941-48A4-8B08-5A95C8BE0899.1.animatedsticker","strong":0,"md5":"c127b5387ad751bca068753a8b9b790a","image":"https:\/\/fb-cdn.fanbook.mobi\/fanbook\/meishe\/SDKLib\/stickerSource2\/BC955A16-8941-48A4-8B08-5A95C8BE0899.png","name":"绝杀","zip":"https:\/\/fb-cdn.fanbook.mobi\/fanbook\/meishe\/SDKLib\/stickerSource2\/BC955A16-8941-48A4-8B08-5A95C8BE0899.zip","lic":"https:\/\/fb-cdn.fanbook.mobi\/fanbook\/meishe\/SDKLib\/sticker\/7-绝杀\/BC955A16-8941-48A4-8B08-5A95C8BE0899.lic"},{"fileName":"13BB78D0-38F5-4CD2-AF07-DEC0EAA0707A.1.animatedsticker","url":"https:\/\/fb-cdn.fanbook.mobi\/fanbook\/meishe\/SDKLib\/stickerSource2\/13BB78D0-38F5-4CD2-AF07-DEC0EAA0707A.1.animatedsticker","strong":0,"md5":"db1caa661a038666a41911e6d379a89f","image":"https:\/\/fb-cdn.fanbook.mobi\/fanbook\/meishe\/SDKLib\/stickerSource2\/13BB78D0-38F5-4CD2-AF07-DEC0EAA0707A.png","name":"中国必胜","zip":"https:\/\/fb-cdn.fanbook.mobi\/fanbook\/meishe\/SDKLib\/stickerSource2\/13BB78D0-38F5-4CD2-AF07-DEC0EAA0707A.zip","lic":"https:\/\/fb-cdn.fanbook.mobi\/fanbook\/meishe\/SDKLib\/sticker\/8-中国必胜\/13BB78D0-38F5-4CD2-AF07-DEC0EAA0707A.lic"},{"fileName":"132D807E-7664-40F9-928B-6DC007E0562C.2.animatedsticker","url":"https:\/\/fb-cdn.fanbook.mobi\/fanbook\/meishe\/SDKLib\/stickerSource2\/132D807E-7664-40F9-928B-6DC007E0562C.2.animatedsticker","strong":0,"md5":"e01992a2721c01bc83724019a66235d8","image":"https:\/\/fb-cdn.fanbook.mobi\/fanbook\/meishe\/SDKLib\/stickerSource2\/132D807E-7664-40F9-928B-6DC007E0562C.png","name":"江湖再见","zip":"https:\/\/fb-cdn.fanbook.mobi\/fanbook\/meishe\/SDKLib\/stickerSource2\/132D807E-7664-40F9-928B-6DC007E0562C.zip","lic":"https:\/\/fb-cdn.fanbook.mobi\/fanbook\/meishe\/SDKLib\/sticker\/9-江湖再见\/132D807E-7664-40F9-928B-6DC007E0562C.lic"},{"fileName":"365A57A3-91BE-42DE-BF7F-A3FF829549C3.2.animatedsticker","url":"https:\/\/fb-cdn.fanbook.mobi\/fanbook\/meishe\/SDKLib\/stickerSource2\/365A57A3-91BE-42DE-BF7F-A3FF829549C3.2.animatedsticker","strong":0,"md5":"936086bf2936a7971a1c1ff719ddb11c","image":"https:\/\/fb-cdn.fanbook.mobi\/fanbook\/meishe\/SDKLib\/stickerSource2\/365A57A3-91BE-42DE-BF7F-A3FF829549C3.png","name":"干饭人","zip":"https:\/\/fb-cdn.fanbook.mobi\/fanbook\/meishe\/SDKLib\/stickerSource2\/365A57A3-91BE-42DE-BF7F-A3FF829549C3.zip","lic":"https:\/\/fb-cdn.fanbook.mobi\/fanbook\/meishe\/SDKLib\/sticker\/10-干饭人\/365A57A3-91BE-42DE-BF7F-A3FF829549C3.lic"},{"fileName":"1FBC7FFD-13E0-4E79-817A-3835E9DC8C55.1.animatedsticker","url":"https:\/\/fb-cdn.fanbook.mobi\/fanbook\/meishe\/SDKLib\/stickerSource2\/1FBC7FFD-13E0-4E79-817A-3835E9DC8C55.1.animatedsticker","strong":0,"md5":"03a3c45d868e07585fb50781bd58f33d","image":"https:\/\/fb-cdn.fanbook.mobi\/fanbook\/meishe\/SDKLib\/stickerSource2\/1FBC7FFD-13E0-4E79-817A-3835E9DC8C55.png","name":"理想的季节","zip":"https:\/\/fb-cdn.fanbook.mobi\/fanbook\/meishe\/SDKLib\/stickerSource2\/1FBC7FFD-13E0-4E79-817A-3835E9DC8C55.zip","lic":"https:\/\/fb-cdn.fanbook.mobi\/fanbook\/meishe\/SDKLib\/sticker\/11-理想的季节\/1FBC7FFD-13E0-4E79-817A-3835E9DC8C55.lic"},{"fileName":"343CFEEE-7F80-46DE-BC43-C21DBD6506A4.2.animatedsticker","url":"https:\/\/fb-cdn.fanbook.mobi\/fanbook\/meishe\/SDKLib\/stickerSource2\/343CFEEE-7F80-46DE-BC43-C21DBD6506A4.2.animatedsticker","strong":0,"md5":"5444af79b79b431dced44242eb96b7b0","image":"https:\/\/fb-cdn.fanbook.mobi\/fanbook\/meishe\/SDKLib\/stickerSource2\/343CFEEE-7F80-46DE-BC43-C21DBD6506A4.webp","name":"最帅的在这里","zip":"https:\/\/fb-cdn.fanbook.mobi\/fanbook\/meishe\/SDKLib\/stickerSource2\/343CFEEE-7F80-46DE-BC43-C21DBD6506A4.zip","lic":"https:\/\/fb-cdn.fanbook.mobi\/fanbook\/meishe\/SDKLib\/sticker\/12-最帅的在这里\/343CFEEE-7F80-46DE-BC43-C21DBD6506A4.lic"},{"fileName":"9889C623-9F81-474F-9B5B-6BF6F60A4CE0.1.animatedsticker","url":"https:\/\/fb-cdn.fanbook.mobi\/fanbook\/meishe\/SDKLib\/stickerSource2\/9889C623-9F81-474F-9B5B-6BF6F60A4CE0.1.animatedsticker","strong":0,"md5":"85df52fb0d0cf89abf8041e79b27304c","image":"https:\/\/fb-cdn.fanbook.mobi\/fanbook\/meishe\/SDKLib\/stickerSource2\/9889C623-9F81-474F-9B5B-6BF6F60A4CE0.webp","name":"棒","zip":"https:\/\/fb-cdn.fanbook.mobi\/fanbook\/meishe\/SDKLib\/stickerSource2\/9889C623-9F81-474F-9B5B-6BF6F60A4CE0.zip","lic":"https:\/\/fb-cdn.fanbook.mobi\/fanbook\/meishe\/SDKLib\/sticker\/13-棒\/9889C623-9F81-474F-9B5B-6BF6F60A4CE0.lic"},{"fileName":"BF6C4F5A-B99E-4F95-91C5-A7845F55309C.1.animatedsticker","url":"https:\/\/fb-cdn.fanbook.mobi\/fanbook\/meishe\/SDKLib\/stickerSource2\/BF6C4F5A-B99E-4F95-91C5-A7845F55309C.1.animatedsticker","strong":0,"md5":"b28a843a0caab19863c57e10df686e98","image":"https:\/\/fb-cdn.fanbook.mobi\/fanbook\/meishe\/SDKLib\/stickerSource2\/BF6C4F5A-B99E-4F95-91C5-A7845F55309C.webp","name":"笔芯","zip":"https:\/\/fb-cdn.fanbook.mobi\/fanbook\/meishe\/SDKLib\/stickerSource2\/BF6C4F5A-B99E-4F95-91C5-A7845F55309C.zip","lic":"https:\/\/fb-cdn.fanbook.mobi\/fanbook\/meishe\/SDKLib\/sticker\/14-笔芯\/BF6C4F5A-B99E-4F95-91C5-A7845F55309C.lic"},{"fileName":"4435FAFE-BDB3-4361-BB5E-15C9F8B025E5.1.animatedsticker","url":"https:\/\/fb-cdn.fanbook.mobi\/fanbook\/meishe\/SDKLib\/stickerSource2\/4435FAFE-BDB3-4361-BB5E-15C9F8B025E5.1.animatedsticker","strong":0,"md5":"93616773bff3c91d44098c1bb7b49652","image":"https:\/\/fb-cdn.fanbook.mobi\/fanbook\/meishe\/SDKLib\/stickerSource2\/4435FAFE-BDB3-4361-BB5E-15C9F8B025E5.webp","name":"爱你哟","zip":"https:\/\/fb-cdn.fanbook.mobi\/fanbook\/meishe\/SDKLib\/stickerSource2\/4435FAFE-BDB3-4361-BB5E-15C9F8B025E5.zip","lic":"https:\/\/fb-cdn.fanbook.mobi\/fanbook\/meishe\/SDKLib\/sticker\/15-爱你哟\/4435FAFE-BDB3-4361-BB5E-15C9F8B025E5.lic"},{"fileName":"E33DAE80-44AA-4D98-B9F8-068C4E15AA4A.1.animatedsticker","url":"https:\/\/fb-cdn.fanbook.mobi\/fanbook\/meishe\/SDKLib\/stickerSource2\/E33DAE80-44AA-4D98-B9F8-068C4E15AA4A.1.animatedsticker","strong":0,"md5":"f578bd91943963279daa6b68c3cf6c77","image":"https:\/\/fb-cdn.fanbook.mobi\/fanbook\/meishe\/SDKLib\/stickerSource2\/E33DAE80-44AA-4D98-B9F8-068C4E15AA4A.webp","name":"彩虹","zip":"https:\/\/fb-cdn.fanbook.mobi\/fanbook\/meishe\/SDKLib\/stickerSource2\/E33DAE80-44AA-4D98-B9F8-068C4E15AA4A.zip","lic":"https:\/\/fb-cdn.fanbook.mobi\/fanbook\/meishe\/SDKLib\/sticker\/16-彩虹\/E33DAE80-44AA-4D98-B9F8-068C4E15AA4A.lic"},{"fileName":"87ACDE9E-8058-42A7-B958-8B9454203968.1.animatedsticker","url":"https:\/\/fb-cdn.fanbook.mobi\/fanbook\/meishe\/SDKLib\/stickerSource2\/87ACDE9E-8058-42A7-B958-8B9454203968.1.animatedsticker","strong":0,"md5":"a2b52ccd0e29913b033101a24b91f82e","image":"https:\/\/fb-cdn.fanbook.mobi\/fanbook\/meishe\/SDKLib\/stickerSource2\/87ACDE9E-8058-42A7-B958-8B9454203968.webp","name":"小花","zip":"https:\/\/fb-cdn.fanbook.mobi\/fanbook\/meishe\/SDKLib\/stickerSource2\/87ACDE9E-8058-42A7-B958-8B9454203968.zip","lic":"https:\/\/fb-cdn.fanbook.mobi\/fanbook\/meishe\/SDKLib\/sticker\/17-小花\/87ACDE9E-8058-42A7-B958-8B9454203968.lic"},{"fileName":"83B5634F-F765-4DD9-8D1A-32FE67747929.1.animatedsticker","url":"https:\/\/fb-cdn.fanbook.mobi\/fanbook\/meishe\/SDKLib\/stickerSource2\/83B5634F-F765-4DD9-8D1A-32FE67747929.1.animatedsticker","strong":0,"md5":"5f006b31b7c0e85ba18f50f3f18f8b80","image":"https:\/\/fb-cdn.fanbook.mobi\/fanbook\/meishe\/SDKLib\/stickerSource2\/83B5634F-F765-4DD9-8D1A-32FE67747929.webp","name":"发射爱心","zip":"https:\/\/fb-cdn.fanbook.mobi\/fanbook\/meishe\/SDKLib\/stickerSource2\/83B5634F-F765-4DD9-8D1A-32FE67747929.zip","lic":"https:\/\/fb-cdn.fanbook.mobi\/fanbook\/meishe\/SDKLib\/sticker\/18-发射爱心\/83B5634F-F765-4DD9-8D1A-32FE67747929.lic"},{"fileName":"445BE49E-F8A5-445B-80CB-1D37FEFDFD5E.2.animatedsticker","url":"https:\/\/fb-cdn.fanbook.mobi\/fanbook\/meishe\/SDKLib\/stickerSource2\/445BE49E-F8A5-445B-80CB-1D37FEFDFD5E.2.animatedsticker","strong":0,"md5":"14ea4a3ed77420619e7ed526c0cb0a99","image":"https:\/\/fb-cdn.fanbook.mobi\/fanbook\/meishe\/SDKLib\/stickerSource2\/445BE49E-F8A5-445B-80CB-1D37FEFDFD5E.webp","name":"小鲜肉","zip":"https:\/\/fb-cdn.fanbook.mobi\/fanbook\/meishe\/SDKLib\/stickerSource2\/445BE49E-F8A5-445B-80CB-1D37FEFDFD5E.zip","lic":"https:\/\/fb-cdn.fanbook.mobi\/fanbook\/meishe\/SDKLib\/sticker\/19-小鲜肉\/445BE49E-F8A5-445B-80CB-1D37FEFDFD5E.lic"},{"fileName":"FFD6AB42-396E-43DE-98BE-A95E3A48159D.2.animatedsticker","url":"https:\/\/fb-cdn.fanbook.mobi\/fanbook\/meishe\/SDKLib\/stickerSource2\/FFD6AB42-396E-43DE-98BE-A95E3A48159D.2.animatedsticker","strong":0,"md5":"112a0a2cca47ee9bc16fa4c586c0a740","image":"https:\/\/fb-cdn.fanbook.mobi\/fanbook\/meishe\/SDKLib\/stickerSource2\/FFD6AB42-396E-43DE-98BE-A95E3A48159D.webp","name":"下雨","zip":"https:\/\/fb-cdn.fanbook.mobi\/fanbook\/meishe\/SDKLib\/stickerSource2\/FFD6AB42-396E-43DE-98BE-A95E3A48159D.zip","lic":"https:\/\/fb-cdn.fanbook.mobi\/fanbook\/meishe\/SDKLib\/sticker\/20-下雨\/FFD6AB42-396E-43DE-98BE-A95E3A48159D.lic"},{"fileName":"FA30F486-F53F-41D0-A0FD-F01857A959B5.2.animatedsticker","url":"https:\/\/fb-cdn.fanbook.mobi\/fanbook\/meishe\/SDKLib\/stickerSource2\/FA30F486-F53F-41D0-A0FD-F01857A959B5.2.animatedsticker","strong":0,"md5":"7231b13133b44164ecb0de06298665ac","image":"https:\/\/fb-cdn.fanbook.mobi\/fanbook\/meishe\/SDKLib\/stickerSource2\/FA30F486-F53F-41D0-A0FD-F01857A959B5.webp","name":"多云","zip":"https:\/\/fb-cdn.fanbook.mobi\/fanbook\/meishe\/SDKLib\/stickerSource2\/FA30F486-F53F-41D0-A0FD-F01857A959B5.zip","lic":"https:\/\/fb-cdn.fanbook.mobi\/fanbook\/meishe\/SDKLib\/sticker\/21-多云\/FA30F486-F53F-41D0-A0FD-F01857A959B5.lic"},{"fileName":"B2A87419-F18B-4B5A-B538-8AFF8F77746F.1.animatedsticker","url":"https:\/\/fb-cdn.fanbook.mobi\/fanbook\/meishe\/SDKLib\/stickerSource2\/B2A87419-F18B-4B5A-B538-8AFF8F77746F.1.animatedsticker","strong":0,"md5":"df5bcb962c1d7702f04e2becf35dd669","image":"https:\/\/fb-cdn.fanbook.mobi\/fanbook\/meishe\/SDKLib\/stickerSource2\/B2A87419-F18B-4B5A-B538-8AFF8F77746F.webp","name":"雷雨","zip":"https:\/\/fb-cdn.fanbook.mobi\/fanbook\/meishe\/SDKLib\/stickerSource2\/B2A87419-F18B-4B5A-B538-8AFF8F77746F.zip","lic":"https:\/\/fb-cdn.fanbook.mobi\/fanbook\/meishe\/SDKLib\/sticker\/22-雷雨\/B2A87419-F18B-4B5A-B538-8AFF8F77746F.lic"},{"fileName":"E7918001-7C52-4C31-B613-C010A63C36EA.1.animatedsticker","url":"https:\/\/fb-cdn.fanbook.mobi\/fanbook\/meishe\/SDKLib\/stickerSource2\/E7918001-7C52-4C31-B613-C010A63C36EA.1.animatedsticker","strong":0,"md5":"b66be72ace36544f3f69f34d2bba8840","image":"https:\/\/fb-cdn.fanbook.mobi\/fanbook\/meishe\/SDKLib\/stickerSource2\/E7918001-7C52-4C31-B613-C010A63C36EA.webp","name":"晴天","zip":"https:\/\/fb-cdn.fanbook.mobi\/fanbook\/meishe\/SDKLib\/stickerSource2\/E7918001-7C52-4C31-B613-C010A63C36EA.zip","lic":"https:\/\/fb-cdn.fanbook.mobi\/fanbook\/meishe\/SDKLib\/sticker\/23-晴天\/E7918001-7C52-4C31-B613-C010A63C36EA.lic"},{"fileName":"DE9D0322-7E9F-42DE-9367-77669A436833.1.animatedsticker","url":"https:\/\/fb-cdn.fanbook.mobi\/fanbook\/meishe\/SDKLib\/stickerSource2\/DE9D0322-7E9F-42DE-9367-77669A436833.1.animatedsticker","strong":0,"md5":"ecc6ecf11bb93b560ebae5fd18bf8b94","image":"https:\/\/fb-cdn.fanbook.mobi\/fanbook\/meishe\/SDKLib\/stickerSource2\/DE9D0322-7E9F-42DE-9367-77669A436833.webp","name":"月亮","zip":"https:\/\/fb-cdn.fanbook.mobi\/fanbook\/meishe\/SDKLib\/stickerSource2\/DE9D0322-7E9F-42DE-9367-77669A436833.zip","lic":"https:\/\/fb-cdn.fanbook.mobi\/fanbook\/meishe\/SDKLib\/sticker\/24-月亮\/DE9D0322-7E9F-42DE-9367-77669A436833.lic"},{"fileName":"FA55DA39-7E2C-4DD4-9798-01F7AE200708.1.animatedsticker","url":"https:\/\/fb-cdn.fanbook.mobi\/fanbook\/meishe\/SDKLib\/stickerSource2\/FA55DA39-7E2C-4DD4-9798-01F7AE200708.1.animatedsticker","strong":0,"md5":"3d54d064794c82f1d61eaa23ec42509d","image":"https:\/\/fb-cdn.fanbook.mobi\/fanbook\/meishe\/SDKLib\/stickerSource2\/FA55DA39-7E2C-4DD4-9798-01F7AE200708.webp","name":"爱心","zip":"https:\/\/fb-cdn.fanbook.mobi\/fanbook\/meishe\/SDKLib\/stickerSource2\/FA55DA39-7E2C-4DD4-9798-01F7AE200708.zip","lic":"https:\/\/fb-cdn.fanbook.mobi\/fanbook\/meishe\/SDKLib\/sticker\/25-爱心\/FA55DA39-7E2C-4DD4-9798-01F7AE200708.lic"},{"fileName":"AFE7B3E1-69F8-4143-AADB-F9A2EE3A46DE.1.animatedsticker","url":"https:\/\/fb-cdn.fanbook.mobi\/fanbook\/meishe\/SDKLib\/stickerSource2\/AFE7B3E1-69F8-4143-AADB-F9A2EE3A46DE.1.animatedsticker","strong":0,"md5":"fe3d46c2f6b3a28646066c3212f83192","image":"https:\/\/fb-cdn.fanbook.mobi\/fanbook\/meishe\/SDKLib\/stickerSource2\/AFE7B3E1-69F8-4143-AADB-F9A2EE3A46DE.png","name":"星空","zip":"https:\/\/fb-cdn.fanbook.mobi\/fanbook\/meishe\/SDKLib\/stickerSource2\/AFE7B3E1-69F8-4143-AADB-F9A2EE3A46DE.zip","lic":"https:\/\/fb-cdn.fanbook.mobi\/fanbook\/meishe\/SDKLib\/sticker\/26-星空\/AFE7B3E1-69F8-4143-AADB-F9A2EE3A46DE.lic"},{"fileName":"8DE93D16-59C8-43C7-B2A5-9BD0E34C46BA.1.animatedsticker","url":"https:\/\/fb-cdn.fanbook.mobi\/fanbook\/meishe\/SDKLib\/stickerSource2\/8DE93D16-59C8-43C7-B2A5-9BD0E34C46BA.1.animatedsticker","strong":0,"md5":"b6974f9dc785783803a56a8f0c1eb49d","image":"https:\/\/fb-cdn.fanbook.mobi\/fanbook\/meishe\/SDKLib\/stickerSource2\/8DE93D16-59C8-43C7-B2A5-9BD0E34C46BA.webp","name":"冰淇淋","zip":"https:\/\/fb-cdn.fanbook.mobi\/fanbook\/meishe\/SDKLib\/stickerSource2\/8DE93D16-59C8-43C7-B2A5-9BD0E34C46BA.zip","lic":"https:\/\/fb-cdn.fanbook.mobi\/fanbook\/meishe\/SDKLib\/sticker\/27-冰淇淋\/8DE93D16-59C8-43C7-B2A5-9BD0E34C46BA.lic"},{"fileName":"66A73430-9E25-4F05-B937-5E47299AE84F.1.animatedsticker","url":"https:\/\/fb-cdn.fanbook.mobi\/fanbook\/meishe\/SDKLib\/stickerSource2\/66A73430-9E25-4F05-B937-5E47299AE84F.1.animatedsticker","strong":0,"md5":"4300eba02aaa74e7e18b4c811e044432","image":"https:\/\/fb-cdn.fanbook.mobi\/fanbook\/meishe\/SDKLib\/stickerSource2\/66A73430-9E25-4F05-B937-5E47299AE84F.webp","name":"甜甜圈","zip":"https:\/\/fb-cdn.fanbook.mobi\/fanbook\/meishe\/SDKLib\/stickerSource2\/66A73430-9E25-4F05-B937-5E47299AE84F.zip","lic":"https:\/\/fb-cdn.fanbook.mobi\/fanbook\/meishe\/SDKLib\/sticker\/28-甜甜圈\/66A73430-9E25-4F05-B937-5E47299AE84F.lic"},{"fileName":"5BB362BE-27D7-4021-A75D-3F9398D3E782.1.animatedsticker","url":"https:\/\/fb-cdn.fanbook.mobi\/fanbook\/meishe\/SDKLib\/stickerSource2\/5BB362BE-27D7-4021-A75D-3F9398D3E782.1.animatedsticker","strong":0,"md5":"aa86e008c1c2932b7e6bf474235b6fda","image":"https:\/\/fb-cdn.fanbook.mobi\/fanbook\/meishe\/SDKLib\/stickerSource2\/5BB362BE-27D7-4021-A75D-3F9398D3E782.webp","name":"LOVE","zip":"https:\/\/fb-cdn.fanbook.mobi\/fanbook\/meishe\/SDKLib\/stickerSource2\/5BB362BE-27D7-4021-A75D-3F9398D3E782.zip","lic":"https:\/\/fb-cdn.fanbook.mobi\/fanbook\/meishe\/SDKLib\/sticker\/29-LOVE\/5BB362BE-27D7-4021-A75D-3F9398D3E782.lic"},{"fileName":"3036EE7B-3154-420A-8D20-6840BD8230A8.1.animatedsticker","url":"https:\/\/fb-cdn.fanbook.mobi\/fanbook\/meishe\/SDKLib\/stickerSource2\/3036EE7B-3154-420A-8D20-6840BD8230A8.1.animatedsticker","strong":0,"md5":"e2a979f8a31bbb20b4a347a0c9a26442","image":"https:\/\/fb-cdn.fanbook.mobi\/fanbook\/meishe\/SDKLib\/stickerSource2\/3036EE7B-3154-420A-8D20-6840BD8230A8.webp","name":"蛋糕","zip":"https:\/\/fb-cdn.fanbook.mobi\/fanbook\/meishe\/SDKLib\/stickerSource2\/3036EE7B-3154-420A-8D20-6840BD8230A8.zip","lic":"https:\/\/fb-cdn.fanbook.mobi\/fanbook\/meishe\/SDKLib\/sticker\/30-蛋糕\/3036EE7B-3154-420A-8D20-6840BD8230A8.lic"},{"fileName":"235240D4-0495-4E9D-B462-60CA3C24DDEF.1.animatedsticker","url":"https:\/\/fb-cdn.fanbook.mobi\/fanbook\/meishe\/SDKLib\/stickerSource2\/235240D4-0495-4E9D-B462-60CA3C24DDEF.1.animatedsticker","strong":0,"md5":"c6360c9c4046a436c44d1a1134085d85","image":"https:\/\/fb-cdn.fanbook.mobi\/fanbook\/meishe\/SDKLib\/stickerSource2\/235240D4-0495-4E9D-B462-60CA3C24DDEF.webp","name":"冰淇淋","zip":"https:\/\/fb-cdn.fanbook.mobi\/fanbook\/meishe\/SDKLib\/stickerSource2\/235240D4-0495-4E9D-B462-60CA3C24DDEF.zip","lic":"https:\/\/fb-cdn.fanbook.mobi\/fanbook\/meishe\/SDKLib\/sticker\/31-冰淇淋\/235240D4-0495-4E9D-B462-60CA3C24DDEF.lic"},{"fileName":"06E26D89-82F9-4115-B98A-47B1F71F88C1.1.animatedsticker","url":"https:\/\/fb-cdn.fanbook.mobi\/fanbook\/meishe\/SDKLib\/stickerSource2\/06E26D89-82F9-4115-B98A-47B1F71F88C1.1.animatedsticker","strong":0,"md5":"3bf7196d69d202ae790f0cd90a328291","image":"https:\/\/fb-cdn.fanbook.mobi\/fanbook\/meishe\/SDKLib\/stickerSource2\/06E26D89-82F9-4115-B98A-47B1F71F88C1.webp","name":"三明治","zip":"https:\/\/fb-cdn.fanbook.mobi\/fanbook\/meishe\/SDKLib\/stickerSource2\/06E26D89-82F9-4115-B98A-47B1F71F88C1.zip","lic":"https:\/\/fb-cdn.fanbook.mobi\/fanbook\/meishe\/SDKLib\/sticker\/32-三明治\/06E26D89-82F9-4115-B98A-47B1F71F88C1.lic"},{"fileName":"0664C2EC-D826-45E2-93F8-7BB6A2D57CAF.2.animatedsticker","url":"https:\/\/fb-cdn.fanbook.mobi\/fanbook\/meishe\/SDKLib\/stickerSource2\/0664C2EC-D826-45E2-93F8-7BB6A2D57CAF.2.animatedsticker","strong":0,"md5":"001651e3a23951158683d435230bb96e","image":"https:\/\/fb-cdn.fanbook.mobi\/fanbook\/meishe\/SDKLib\/stickerSource2\/0664C2EC-D826-45E2-93F8-7BB6A2D57CAF.webp","name":"哭泣","zip":"https:\/\/fb-cdn.fanbook.mobi\/fanbook\/meishe\/SDKLib\/stickerSource2\/0664C2EC-D826-45E2-93F8-7BB6A2D57CAF.zip","lic":"https:\/\/fb-cdn.fanbook.mobi\/fanbook\/meishe\/SDKLib\/sticker\/33-哭泣\/0664C2EC-D826-45E2-93F8-7BB6A2D57CAF.lic"},{"fileName":"38AD5389-5B25-4750-A245-D464A0FB665D.2.animatedsticker","url":"https:\/\/fb-cdn.fanbook.mobi\/fanbook\/meishe\/SDKLib\/stickerSource2\/38AD5389-5B25-4750-A245-D464A0FB665D.2.animatedsticker","strong":0,"md5":"7c5b0e9180d4354272618d05742a7c85","image":"https:\/\/fb-cdn.fanbook.mobi\/fanbook\/meishe\/SDKLib\/stickerSource2\/38AD5389-5B25-4750-A245-D464A0FB665D.webp","name":"冒星星","zip":"https:\/\/fb-cdn.fanbook.mobi\/fanbook\/meishe\/SDKLib\/stickerSource2\/38AD5389-5B25-4750-A245-D464A0FB665D.zip","lic":"https:\/\/fb-cdn.fanbook.mobi\/fanbook\/meishe\/SDKLib\/sticker\/34-冒星星\/38AD5389-5B25-4750-A245-D464A0FB665D.lic"},{"fileName":"385F5BFD-C614-4E70-84C8-99B0DF401AF0.2.animatedsticker","url":"https:\/\/fb-cdn.fanbook.mobi\/fanbook\/meishe\/SDKLib\/stickerSource2\/385F5BFD-C614-4E70-84C8-99B0DF401AF0.2.animatedsticker","strong":0,"md5":"dffae3f029cfc58eee2445d61b354dcd","image":"https:\/\/fb-cdn.fanbook.mobi\/fanbook\/meishe\/SDKLib\/stickerSource2\/385F5BFD-C614-4E70-84C8-99B0DF401AF0.webp","name":"温度计","zip":"https:\/\/fb-cdn.fanbook.mobi\/fanbook\/meishe\/SDKLib\/stickerSource2\/385F5BFD-C614-4E70-84C8-99B0DF401AF0.zip","lic":"https:\/\/fb-cdn.fanbook.mobi\/fanbook\/meishe\/SDKLib\/sticker\/35-温度计\/385F5BFD-C614-4E70-84C8-99B0DF401AF0.lic"},{"fileName":"EFE492CB-4D49-4A76-BABF-0A5574DBF912.1.animatedsticker","url":"https:\/\/fb-cdn.fanbook.mobi\/fanbook\/meishe\/SDKLib\/stickerSource2\/EFE492CB-4D49-4A76-BABF-0A5574DBF912.1.animatedsticker","strong":0,"md5":"3b0a23168d3ce6db2ddf845ce49683e8","image":"https:\/\/fb-cdn.fanbook.mobi\/fanbook\/meishe\/SDKLib\/stickerSource2\/EFE492CB-4D49-4A76-BABF-0A5574DBF912.png","name":"游戏","zip":"https:\/\/fb-cdn.fanbook.mobi\/fanbook\/meishe\/SDKLib\/stickerSource2\/EFE492CB-4D49-4A76-BABF-0A5574DBF912.zip","lic":"https:\/\/fb-cdn.fanbook.mobi\/fanbook\/meishe\/SDKLib\/sticker\/36-游戏\/EFE492CB-4D49-4A76-BABF-0A5574DBF912.lic"},{"fileName":"D6304EDD-1EE6-4FE5-8940-77AECB49568C.1.animatedsticker","url":"https:\/\/fb-cdn.fanbook.mobi\/fanbook\/meishe\/SDKLib\/stickerSource2\/D6304EDD-1EE6-4FE5-8940-77AECB49568C.1.animatedsticker","strong":0,"md5":"bbf23045f222ed8cd7491155bff88062","image":"https:\/\/fb-cdn.fanbook.mobi\/fanbook\/meishe\/SDKLib\/stickerSource2\/D6304EDD-1EE6-4FE5-8940-77AECB49568C.webp","name":"爱心","zip":"https:\/\/fb-cdn.fanbook.mobi\/fanbook\/meishe\/SDKLib\/stickerSource2\/D6304EDD-1EE6-4FE5-8940-77AECB49568C.zip","lic":"https:\/\/fb-cdn.fanbook.mobi\/fanbook\/meishe\/SDKLib\/sticker\/37-爱心\/D6304EDD-1EE6-4FE5-8940-77AECB49568C.lic"},{"fileName":"129ED816-7A39-4A9E-BB0F-4CD7819DD6F2.1.animatedsticker","url":"https:\/\/fb-cdn.fanbook.mobi\/fanbook\/meishe\/SDKLib\/stickerSource2\/129ED816-7A39-4A9E-BB0F-4CD7819DD6F2.1.animatedsticker","strong":0,"md5":"1ce2ffcec55609879c08a2c4edbaf069","image":"https:\/\/fb-cdn.fanbook.mobi\/fanbook\/meishe\/SDKLib\/stickerSource2\/129ED816-7A39-4A9E-BB0F-4CD7819DD6F2.webp","name":"害羞","zip":"https:\/\/fb-cdn.fanbook.mobi\/fanbook\/meishe\/SDKLib\/stickerSource2\/129ED816-7A39-4A9E-BB0F-4CD7819DD6F2.zip","lic":"https:\/\/fb-cdn.fanbook.mobi\/fanbook\/meishe\/SDKLib\/sticker\/38-害羞\/129ED816-7A39-4A9E-BB0F-4CD7819DD6F2.lic"},{"fileName":"7EA19AB7-8C47-4CD5-8F69-91A8C3C8A8B5.1.animatedsticker","url":"https:\/\/fb-cdn.fanbook.mobi\/fanbook\/meishe\/SDKLib\/stickerSource2\/7EA19AB7-8C47-4CD5-8F69-91A8C3C8A8B5.1.animatedsticker","strong":0,"md5":"408ed9d608c5fa179e3f2d6cd9014d93","image":"https:\/\/fb-cdn.fanbook.mobi\/fanbook\/meishe\/SDKLib\/stickerSource2\/7EA19AB7-8C47-4CD5-8F69-91A8C3C8A8B5.webp","name":"可怜","zip":"https:\/\/fb-cdn.fanbook.mobi\/fanbook\/meishe\/SDKLib\/stickerSource2\/7EA19AB7-8C47-4CD5-8F69-91A8C3C8A8B5.zip","lic":"https:\/\/fb-cdn.fanbook.mobi\/fanbook\/meishe\/SDKLib\/sticker\/39-可怜\/7EA19AB7-8C47-4CD5-8F69-91A8C3C8A8B5.lic"},{"fileName":"6D06C181-F907-4A23-923C-E9AD1D8514BB.1.animatedsticker","url":"https:\/\/fb-cdn.fanbook.mobi\/fanbook\/meishe\/SDKLib\/stickerSource2\/6D06C181-F907-4A23-923C-E9AD1D8514BB.1.animatedsticker","strong":0,"md5":"6d96a92a2c39b2aab5a4df2523c2ed5b","image":"https:\/\/fb-cdn.fanbook.mobi\/fanbook\/meishe\/SDKLib\/stickerSource2\/6D06C181-F907-4A23-923C-E9AD1D8514BB.webp","name":"比心","zip":"https:\/\/fb-cdn.fanbook.mobi\/fanbook\/meishe\/SDKLib\/stickerSource2\/6D06C181-F907-4A23-923C-E9AD1D8514BB.zip","lic":"https:\/\/fb-cdn.fanbook.mobi\/fanbook\/meishe\/SDKLib\/sticker\/40-比心\/6D06C181-F907-4A23-923C-E9AD1D8514BB.lic"},{"fileName":"4F39B8B1-0232-4C4A-926E-831FE5EB94DC.1.animatedsticker","url":"https:\/\/fb-cdn.fanbook.mobi\/fanbook\/meishe\/SDKLib\/stickerSource2\/4F39B8B1-0232-4C4A-926E-831FE5EB94DC.1.animatedsticker","strong":0,"md5":"cd354ea9dd1e49b0513d4b28ee898a0d","image":"https:\/\/fb-cdn.fanbook.mobi\/fanbook\/meishe\/SDKLib\/stickerSource2\/4F39B8B1-0232-4C4A-926E-831FE5EB94DC.webp","name":"‡е","zip":"https:\/\/fb-cdn.fanbook.mobi\/fanbook\/meishe\/SDKLib\/stickerSource2\/4F39B8B1-0232-4C4A-926E-831FE5EB94DC.zip","lic":"https:\/\/fb-cdn.fanbook.mobi\/fanbook\/meishe\/SDKLib\/sticker\/41-‡е\/4F39B8B1-0232-4C4A-926E-831FE5EB94DC.lic"},{"fileName":"3E99427B-D99C-481C-9E00-DAD951C329B7.1.animatedsticker","url":"https:\/\/fb-cdn.fanbook.mobi\/fanbook\/meishe\/SDKLib\/stickerSource2\/3E99427B-D99C-481C-9E00-DAD951C329B7.1.animatedsticker","strong":0,"md5":"0537b4aec9bd99a98f5de3e0f90585d2","image":"https:\/\/fb-cdn.fanbook.mobi\/fanbook\/meishe\/SDKLib\/stickerSource2\/3E99427B-D99C-481C-9E00-DAD951C329B7.webp","name":"大笑","zip":"https:\/\/fb-cdn.fanbook.mobi\/fanbook\/meishe\/SDKLib\/stickerSource2\/3E99427B-D99C-481C-9E00-DAD951C329B7.zip","lic":"https:\/\/fb-cdn.fanbook.mobi\/fanbook\/meishe\/SDKLib\/sticker\/43-大笑\/3E99427B-D99C-481C-9E00-DAD951C329B7.lic"},{"fileName":"D692A996-75E9-4395-8606-1802C638A595.1.animatedsticker","url":"https:\/\/fb-cdn.fanbook.mobi\/fanbook\/meishe\/SDKLib\/stickerSource2\/D692A996-75E9-4395-8606-1802C638A595.1.animatedsticker","strong":0,"md5":"5d43996deaf20b9852e4c311dc90399d","image":"https:\/\/fb-cdn.fanbook.mobi\/fanbook\/meishe\/SDKLib\/stickerSource2\/D692A996-75E9-4395-8606-1802C638A595.webp","name":"晕","zip":"https:\/\/fb-cdn.fanbook.mobi\/fanbook\/meishe\/SDKLib\/stickerSource2\/D692A996-75E9-4395-8606-1802C638A595.zip","lic":"https:\/\/fb-cdn.fanbook.mobi\/fanbook\/meishe\/SDKLib\/sticker\/44-晕\/D692A996-75E9-4395-8606-1802C638A595.lic"},{"fileName":"A5CB70AC-901D-4A89-81CD-F24E7E4C5409.1.animatedsticker","url":"https:\/\/fb-cdn.fanbook.mobi\/fanbook\/meishe\/SDKLib\/stickerSource2\/A5CB70AC-901D-4A89-81CD-F24E7E4C5409.1.animatedsticker","strong":0,"md5":"f277e3009a01e037fc0f9e130da9b706","image":"https:\/\/fb-cdn.fanbook.mobi\/fanbook\/meishe\/SDKLib\/stickerSource2\/A5CB70AC-901D-4A89-81CD-F24E7E4C5409.webp","name":"么么哒","zip":"https:\/\/fb-cdn.fanbook.mobi\/fanbook\/meishe\/SDKLib\/stickerSource2\/A5CB70AC-901D-4A89-81CD-F24E7E4C5409.zip","lic":"https:\/\/fb-cdn.fanbook.mobi\/fanbook\/meishe\/SDKLib\/sticker\/45-么么哒\/A5CB70AC-901D-4A89-81CD-F24E7E4C5409.lic"},{"fileName":"EA34B6A6-7045-43A6-A3C7-B2D02EF2E2EC.1.animatedsticker","url":"https:\/\/fb-cdn.fanbook.mobi\/fanbook\/meishe\/SDKLib\/stickerSource2\/EA34B6A6-7045-43A6-A3C7-B2D02EF2E2EC.1.animatedsticker","strong":0,"md5":"284a88a81257aab740ebf02929cc12c6","image":"https:\/\/fb-cdn.fanbook.mobi\/fanbook\/meishe\/SDKLib\/stickerSource2\/EA34B6A6-7045-43A6-A3C7-B2D02EF2E2EC.webp","name":"呆住","zip":"https:\/\/fb-cdn.fanbook.mobi\/fanbook\/meishe\/SDKLib\/stickerSource2\/EA34B6A6-7045-43A6-A3C7-B2D02EF2E2EC.zip","lic":"https:\/\/fb-cdn.fanbook.mobi\/fanbook\/meishe\/SDKLib\/sticker\/46-呆住\/EA34B6A6-7045-43A6-A3C7-B2D02EF2E2EC.lic"},{"fileName":"E651140B-B085-4C94-9BFE-E25B4EEC22DF.1.animatedsticker","url":"https:\/\/fb-cdn.fanbook.mobi\/fanbook\/meishe\/SDKLib\/stickerSource2\/E651140B-B085-4C94-9BFE-E25B4EEC22DF.1.animatedsticker","strong":0,"md5":"2c2c12ef875b382b0055f13ae60fd59f","image":"https:\/\/fb-cdn.fanbook.mobi\/fanbook\/meishe\/SDKLib\/stickerSource2\/E651140B-B085-4C94-9BFE-E25B4EEC22DF.webp","name":"生气","zip":"https:\/\/fb-cdn.fanbook.mobi\/fanbook\/meishe\/SDKLib\/stickerSource2\/E651140B-B085-4C94-9BFE-E25B4EEC22DF.zip","lic":"https:\/\/fb-cdn.fanbook.mobi\/fanbook\/meishe\/SDKLib\/sticker\/47-生气\/E651140B-B085-4C94-9BFE-E25B4EEC22DF.lic"},{"fileName":"46D3BDC7-2F79-42E1-98D2-2D4FFCB2542C.1.animatedsticker","url":"https:\/\/fb-cdn.fanbook.mobi\/fanbook\/meishe\/SDKLib\/stickerSource2\/46D3BDC7-2F79-42E1-98D2-2D4FFCB2542C.1.animatedsticker","strong":0,"md5":"7b2785ab6610b181c90ca392af5c497b","image":"https:\/\/fb-cdn.fanbook.mobi\/fanbook\/meishe\/SDKLib\/stickerSource2\/46D3BDC7-2F79-42E1-98D2-2D4FFCB2542C.webp","name":"红包","zip":"https:\/\/fb-cdn.fanbook.mobi\/fanbook\/meishe\/SDKLib\/stickerSource2\/46D3BDC7-2F79-42E1-98D2-2D4FFCB2542C.zip","lic":"https:\/\/fb-cdn.fanbook.mobi\/fanbook\/meishe\/SDKLib\/sticker\/48-红包\/46D3BDC7-2F79-42E1-98D2-2D4FFCB2542C.lic"},{"fileName":"DBC587B1-F908-4294-8B1C-1D6C40622890.1.animatedsticker","url":"https:\/\/fb-cdn.fanbook.mobi\/fanbook\/meishe\/SDKLib\/stickerSource2\/DBC587B1-F908-4294-8B1C-1D6C40622890.1.animatedsticker","strong":0,"md5":"589d5c6358067b2b7f7dee9f6c31383f","image":"https:\/\/fb-cdn.fanbook.mobi\/fanbook\/meishe\/SDKLib\/stickerSource2\/DBC587B1-F908-4294-8B1C-1D6C40622890.webp","name":"虎年大吉","zip":"https:\/\/fb-cdn.fanbook.mobi\/fanbook\/meishe\/SDKLib\/stickerSource2\/DBC587B1-F908-4294-8B1C-1D6C40622890.zip","lic":"https:\/\/fb-cdn.fanbook.mobi\/fanbook\/meishe\/SDKLib\/sticker\/49-虎年大吉\/DBC587B1-F908-4294-8B1C-1D6C40622890.lic"},{"fileName":"BDFC7054-1CFF-4D44-BA50-17590F564DC4.1.animatedsticker","url":"https:\/\/fb-cdn.fanbook.mobi\/fanbook\/meishe\/SDKLib\/stickerSource2\/BDFC7054-1CFF-4D44-BA50-17590F564DC4.1.animatedsticker","strong":0,"md5":"871de5ae73f601d274e77b876052fb11","image":"https:\/\/fb-cdn.fanbook.mobi\/fanbook\/meishe\/SDKLib\/stickerSource2\/BDFC7054-1CFF-4D44-BA50-17590F564DC4.webp","name":"虎年大吉","zip":"https:\/\/fb-cdn.fanbook.mobi\/fanbook\/meishe\/SDKLib\/stickerSource2\/BDFC7054-1CFF-4D44-BA50-17590F564DC4.zip","lic":"https:\/\/fb-cdn.fanbook.mobi\/fanbook\/meishe\/SDKLib\/sticker\/50-虎年大吉\/BDFC7054-1CFF-4D44-BA50-17590F564DC4.lic"},{"fileName":"9A651D89-89A7-438D-9017-A9949D252708.1.animatedsticker","url":"https:\/\/fb-cdn.fanbook.mobi\/fanbook\/meishe\/SDKLib\/stickerSource2\/9A651D89-89A7-438D-9017-A9949D252708.1.animatedsticker","strong":0,"md5":"91fb47fb2601f923e692353a41a9ef1c","image":"https:\/\/fb-cdn.fanbook.mobi\/fanbook\/meishe\/SDKLib\/stickerSource2\/9A651D89-89A7-438D-9017-A9949D252708.webp","name":"虎年大吉","zip":"https:\/\/fb-cdn.fanbook.mobi\/fanbook\/meishe\/SDKLib\/stickerSource2\/9A651D89-89A7-438D-9017-A9949D252708.zip","lic":"https:\/\/fb-cdn.fanbook.mobi\/fanbook\/meishe\/SDKLib\/sticker\/51-虎年大吉\/9A651D89-89A7-438D-9017-A9949D252708.lic"},{"fileName":"CF68DD04-6B29-4425-BB50-A1E113A2562A.1.animatedsticker","url":"https:\/\/fb-cdn.fanbook.mobi\/fanbook\/meishe\/SDKLib\/stickerSource2\/CF68DD04-6B29-4425-BB50-A1E113A2562A.1.animatedsticker","strong":0,"md5":"9b8c6a4cac35d8438b21ab2086628ee2","image":"https:\/\/fb-cdn.fanbook.mobi\/fanbook\/meishe\/SDKLib\/stickerSource2\/CF68DD04-6B29-4425-BB50-A1E113A2562A.webp","name":"气泡","zip":"https:\/\/fb-cdn.fanbook.mobi\/fanbook\/meishe\/SDKLib\/stickerSource2\/CF68DD04-6B29-4425-BB50-A1E113A2562A.zip","lic":"https:\/\/fb-cdn.fanbook.mobi\/fanbook\/meishe\/SDKLib\/sticker\/52-气泡\/CF68DD04-6B29-4425-BB50-A1E113A2562A.lic"},{"fileName":"4D39FAF2-82CD-4117-8F88-9821C9B44FCC.1.animatedsticker","url":"https:\/\/fb-cdn.fanbook.mobi\/fanbook\/meishe\/SDKLib\/stickerSource2\/4D39FAF2-82CD-4117-8F88-9821C9B44FCC.1.animatedsticker","strong":0,"md5":"e9684de521a273be95878f0fce58dc2c","image":"https:\/\/fb-cdn.fanbook.mobi\/fanbook\/meishe\/SDKLib\/stickerSource2\/4D39FAF2-82CD-4117-8F88-9821C9B44FCC.webp","name":"泡泡","zip":"https:\/\/fb-cdn.fanbook.mobi\/fanbook\/meishe\/SDKLib\/stickerSource2\/4D39FAF2-82CD-4117-8F88-9821C9B44FCC.zip","lic":"https:\/\/fb-cdn.fanbook.mobi\/fanbook\/meishe\/SDKLib\/sticker\/53-泡泡\/4D39FAF2-82CD-4117-8F88-9821C9B44FCC.lic"},{"fileName":"B1B3394D-95AC-46F7-BE1E-77A1A55967DE.1.animatedsticker","url":"https:\/\/fb-cdn.fanbook.mobi\/fanbook\/meishe\/SDKLib\/stickerSource2\/B1B3394D-95AC-46F7-BE1E-77A1A55967DE.1.animatedsticker","strong":0,"md5":"5866dd1ff8c7f2ab3b54986f25fc59c2","image":"https:\/\/fb-cdn.fanbook.mobi\/fanbook\/meishe\/SDKLib\/stickerSource2\/B1B3394D-95AC-46F7-BE1E-77A1A55967DE.webp","name":"打击","zip":"https:\/\/fb-cdn.fanbook.mobi\/fanbook\/meishe\/SDKLib\/stickerSource2\/B1B3394D-95AC-46F7-BE1E-77A1A55967DE.zip","lic":"https:\/\/fb-cdn.fanbook.mobi\/fanbook\/meishe\/SDKLib\/sticker\/54-打击\/B1B3394D-95AC-46F7-BE1E-77A1A55967DE.lic"},{"fileName":"30D8D375-C036-4ED9-AE49-94FC42D4F511.1.animatedsticker","url":"https:\/\/fb-cdn.fanbook.mobi\/fanbook\/meishe\/SDKLib\/stickerSource2\/30D8D375-C036-4ED9-AE49-94FC42D4F511.1.animatedsticker","strong":0,"md5":"6e1eb569a94327f37bdf20ecf7d08152","image":"https:\/\/fb-cdn.fanbook.mobi\/fanbook\/meishe\/SDKLib\/stickerSource2\/30D8D375-C036-4ED9-AE49-94FC42D4F511.webp","name":"刀光剑影","zip":"https:\/\/fb-cdn.fanbook.mobi\/fanbook\/meishe\/SDKLib\/stickerSource2\/30D8D375-C036-4ED9-AE49-94FC42D4F511.zip","lic":"https:\/\/fb-cdn.fanbook.mobi\/fanbook\/meishe\/SDKLib\/sticker\/55-刀光剑影\/30D8D375-C036-4ED9-AE49-94FC42D4F511.lic"},{"fileName":"4E639BA4-BCE9-414F-93D9-B55F7051373F.1.animatedsticker","url":"https:\/\/fb-cdn.fanbook.mobi\/fanbook\/meishe\/SDKLib\/stickerSource2\/4E639BA4-BCE9-414F-93D9-B55F7051373F.1.animatedsticker","strong":0,"md5":"1f640e6fdcb7fbaf40c9732502024629","image":"https:\/\/fb-cdn.fanbook.mobi\/fanbook\/meishe\/SDKLib\/stickerSource2\/4E639BA4-BCE9-414F-93D9-B55F7051373F.webp","name":"猫咪","zip":"https:\/\/fb-cdn.fanbook.mobi\/fanbook\/meishe\/SDKLib\/stickerSource2\/4E639BA4-BCE9-414F-93D9-B55F7051373F.zip","lic":"https:\/\/fb-cdn.fanbook.mobi\/fanbook\/meishe\/SDKLib\/sticker\/56-猫咪\/4E639BA4-BCE9-414F-93D9-B55F7051373F.lic"},{"fileName":"7005DDF3-FDC3-4D87-A599-F32C4A938F0B.1.animatedsticker","url":"https:\/\/fb-cdn.fanbook.mobi\/fanbook\/meishe\/SDKLib\/stickerSource2\/7005DDF3-FDC3-4D87-A599-F32C4A938F0B.1.animatedsticker","strong":0,"md5":"c040c1a7432ef1edf6cc13319a532b9c","image":"https:\/\/fb-cdn.fanbook.mobi\/fanbook\/meishe\/SDKLib\/stickerSource2\/7005DDF3-FDC3-4D87-A599-F32C4A938F0B.webp","name":"萝卜兔","zip":"https:\/\/fb-cdn.fanbook.mobi\/fanbook\/meishe\/SDKLib\/stickerSource2\/7005DDF3-FDC3-4D87-A599-F32C4A938F0B.zip","lic":"https:\/\/fb-cdn.fanbook.mobi\/fanbook\/meishe\/SDKLib\/sticker\/57-萝卜兔\/7005DDF3-FDC3-4D87-A599-F32C4A938F0B.lic"},{"fileName":"929EE0FA-227F-4DBE-BB91-4B8230154A5F.1.animatedsticker","url":"https:\/\/fb-cdn.fanbook.mobi\/fanbook\/meishe\/SDKLib\/stickerSource2\/929EE0FA-227F-4DBE-BB91-4B8230154A5F.1.animatedsticker","strong":0,"md5":"637160e2dce7227f2d66e9b9e2cfe371","image":"https:\/\/fb-cdn.fanbook.mobi\/fanbook\/meishe\/SDKLib\/stickerSource2\/929EE0FA-227F-4DBE-BB91-4B8230154A5F.png","name":"眼镜","zip":"https:\/\/fb-cdn.fanbook.mobi\/fanbook\/meishe\/SDKLib\/stickerSource2\/929EE0FA-227F-4DBE-BB91-4B8230154A5F.zip","lic":"https:\/\/fb-cdn.fanbook.mobi\/fanbook\/meishe\/SDKLib\/sticker\/58-眼镜\/929EE0FA-227F-4DBE-BB91-4B8230154A5F.lic"},{"fileName":"D6396AE0-17D9-4767-BADD-54AE9CF5FF22.1.animatedsticker","url":"https:\/\/fb-cdn.fanbook.mobi\/fanbook\/meishe\/SDKLib\/stickerSource2\/D6396AE0-17D9-4767-BADD-54AE9CF5FF22.1.animatedsticker","strong":0,"md5":"35e7100131e42e4c6a9c363e2df98976","image":"https:\/\/fb-cdn.fanbook.mobi\/fanbook\/meishe\/SDKLib\/stickerSource2\/D6396AE0-17D9-4767-BADD-54AE9CF5FF22.png","name":"领带","zip":"https:\/\/fb-cdn.fanbook.mobi\/fanbook\/meishe\/SDKLib\/stickerSource2\/D6396AE0-17D9-4767-BADD-54AE9CF5FF22.zip","lic":"https:\/\/fb-cdn.fanbook.mobi\/fanbook\/meishe\/SDKLib\/sticker\/59-领带\/D6396AE0-17D9-4767-BADD-54AE9CF5FF22.lic"},{"fileName":"4BB00F98-A35E-4964-8D44-589495C97544.1.animatedsticker","url":"https:\/\/fb-cdn.fanbook.mobi\/fanbook\/meishe\/SDKLib\/stickerSource2\/4BB00F98-A35E-4964-8D44-589495C97544.1.animatedsticker","strong":0,"md5":"f2b0400ac219bea24c5076a19148f7f4","image":"https:\/\/fb-cdn.fanbook.mobi\/fanbook\/meishe\/SDKLib\/stickerSource2\/4BB00F98-A35E-4964-8D44-589495C97544.png","name":"围脖","zip":"https:\/\/fb-cdn.fanbook.mobi\/fanbook\/meishe\/SDKLib\/stickerSource2\/4BB00F98-A35E-4964-8D44-589495C97544.zip","lic":"https:\/\/fb-cdn.fanbook.mobi\/fanbook\/meishe\/SDKLib\/sticker\/60-围脖\/4BB00F98-A35E-4964-8D44-589495C97544.lic"},{"fileName":"386503AA-74CC-4B77-AFCC-B66283A21183.1.animatedsticker","url":"https:\/\/fb-cdn.fanbook.mobi\/fanbook\/meishe\/SDKLib\/stickerSource2\/386503AA-74CC-4B77-AFCC-B66283A21183.1.animatedsticker","strong":0,"md5":"d675a37aece7775a2f3d712217d5606b","image":"https:\/\/fb-cdn.fanbook.mobi\/fanbook\/meishe\/SDKLib\/stickerSource2\/386503AA-74CC-4B77-AFCC-B66283A21183.png","name":"胸章","zip":"https:\/\/fb-cdn.fanbook.mobi\/fanbook\/meishe\/SDKLib\/stickerSource2\/386503AA-74CC-4B77-AFCC-B66283A21183.zip","lic":"https:\/\/fb-cdn.fanbook.mobi\/fanbook\/meishe\/SDKLib\/sticker\/61-胸章\/386503AA-74CC-4B77-AFCC-B66283A21183.lic"},{"fileName":"AAFDCC7C-5B72-4DC8-9A18-C681712F06FD.1.animatedsticker","url":"https:\/\/fb-cdn.fanbook.mobi\/fanbook\/meishe\/SDKLib\/stickerSource2\/AAFDCC7C-5B72-4DC8-9A18-C681712F06FD.1.animatedsticker","strong":0,"md5":"8d1a8cae559bd47eed4c85e98393265a","image":"https:\/\/fb-cdn.fanbook.mobi\/fanbook\/meishe\/SDKLib\/stickerSource2\/AAFDCC7C-5B72-4DC8-9A18-C681712F06FD.webp","name":"爱心兔","zip":"https:\/\/fb-cdn.fanbook.mobi\/fanbook\/meishe\/SDKLib\/stickerSource2\/AAFDCC7C-5B72-4DC8-9A18-C681712F06FD.zip","lic":"https:\/\/fb-cdn.fanbook.mobi\/fanbook\/meishe\/SDKLib\/sticker\/62-爱心兔\/AAFDCC7C-5B72-4DC8-9A18-C681712F06FD.lic"},{"fileName":"BC5756DE-37F6-41C2-835A-044FF1E0A6CF.1.animatedsticker","url":"https:\/\/fb-cdn.fanbook.mobi\/fanbook\/meishe\/SDKLib\/stickerSource2\/BC5756DE-37F6-41C2-835A-044FF1E0A6CF.1.animatedsticker","strong":0,"md5":"dd9c7c7056bffc4bd625da7ad11459fc","image":"https:\/\/fb-cdn.fanbook.mobi\/fanbook\/meishe\/SDKLib\/stickerSource2\/BC5756DE-37F6-41C2-835A-044FF1E0A6CF.webp","name":"爱心熊","zip":"https:\/\/fb-cdn.fanbook.mobi\/fanbook\/meishe\/SDKLib\/stickerSource2\/BC5756DE-37F6-41C2-835A-044FF1E0A6CF.zip","lic":"https:\/\/fb-cdn.fanbook.mobi\/fanbook\/meishe\/SDKLib\/sticker\/63-爱心熊\/BC5756DE-37F6-41C2-835A-044FF1E0A6CF.lic"},{"fileName":"219B1838-F178-4CFA-951A-1FEE81A42D1C.1.animatedsticker","url":"https:\/\/fb-cdn.fanbook.mobi\/fanbook\/meishe\/SDKLib\/stickerSource2\/219B1838-F178-4CFA-951A-1FEE81A42D1C.1.animatedsticker","strong":0,"md5":"1619e9525b1acde10627ec4645099044","image":"https:\/\/fb-cdn.fanbook.mobi\/fanbook\/meishe\/SDKLib\/stickerSource2\/219B1838-F178-4CFA-951A-1FEE81A42D1C.webp","name":"像素点赞","zip":"https:\/\/fb-cdn.fanbook.mobi\/fanbook\/meishe\/SDKLib\/stickerSource2\/219B1838-F178-4CFA-951A-1FEE81A42D1C.zip","lic":"https:\/\/fb-cdn.fanbook.mobi\/fanbook\/meishe\/SDKLib\/sticker\/64-像素点赞\/219B1838-F178-4CFA-951A-1FEE81A42D1C.lic"},{"fileName":"B21C601C-F309-4A42-A371-172486B8E5CB.1.animatedsticker","url":"https:\/\/fb-cdn.fanbook.mobi\/fanbook\/meishe\/SDKLib\/stickerSource2\/B21C601C-F309-4A42-A371-172486B8E5CB.1.animatedsticker","strong":0,"md5":"6bb51cda040f96fc077af829907f9703","image":"https:\/\/fb-cdn.fanbook.mobi\/fanbook\/meishe\/SDKLib\/stickerSource2\/B21C601C-F309-4A42-A371-172486B8E5CB.png","name":"像素笑脸","zip":"https:\/\/fb-cdn.fanbook.mobi\/fanbook\/meishe\/SDKLib\/stickerSource2\/B21C601C-F309-4A42-A371-172486B8E5CB.zip","lic":"https:\/\/fb-cdn.fanbook.mobi\/fanbook\/meishe\/SDKLib\/sticker\/65-像素笑脸\/B21C601C-F309-4A42-A371-172486B8E5CB.lic"},{"fileName":"8FBEBB78-2BA5-4B6A-9F07-0A0B158944AD.1.animatedsticker","url":"https:\/\/fb-cdn.fanbook.mobi\/fanbook\/meishe\/SDKLib\/stickerSource2\/8FBEBB78-2BA5-4B6A-9F07-0A0B158944AD.1.animatedsticker","strong":0,"md5":"9e34b4dd943db8fcc3656c9b49184e9b","image":"https:\/\/fb-cdn.fanbook.mobi\/fanbook\/meishe\/SDKLib\/stickerSource2\/8FBEBB78-2BA5-4B6A-9F07-0A0B158944AD.webp","name":"像素奖杯","zip":"https:\/\/fb-cdn.fanbook.mobi\/fanbook\/meishe\/SDKLib\/stickerSource2\/8FBEBB78-2BA5-4B6A-9F07-0A0B158944AD.zip","lic":"https:\/\/fb-cdn.fanbook.mobi\/fanbook\/meishe\/SDKLib\/sticker\/66-像素奖杯\/8FBEBB78-2BA5-4B6A-9F07-0A0B158944AD.lic"},{"fileName":"C0631600-0925-4628-9564-DB4DAD527AC6.1.animatedsticker","url":"https:\/\/fb-cdn.fanbook.mobi\/fanbook\/meishe\/SDKLib\/stickerSource2\/C0631600-0925-4628-9564-DB4DAD527AC6.1.animatedsticker","strong":0,"md5":"37d42ae179736fedf37cde0f84984970","image":"https:\/\/fb-cdn.fanbook.mobi\/fanbook\/meishe\/SDKLib\/stickerSource2\/C0631600-0925-4628-9564-DB4DAD527AC6.webp","name":"像素对话框","zip":"https:\/\/fb-cdn.fanbook.mobi\/fanbook\/meishe\/SDKLib\/stickerSource2\/C0631600-0925-4628-9564-DB4DAD527AC6.zip","lic":"https:\/\/fb-cdn.fanbook.mobi\/fanbook\/meishe\/SDKLib\/sticker\/67-像素对话框\/C0631600-0925-4628-9564-DB4DAD527AC6.lic"},{"fileName":"63C46D07-79E9-4E60-AA7D-AABADB78F1BC.1.animatedsticker","url":"https:\/\/fb-cdn.fanbook.mobi\/fanbook\/meishe\/SDKLib\/stickerSource2\/63C46D07-79E9-4E60-AA7D-AABADB78F1BC.1.animatedsticker","strong":0,"md5":"1a1f76356bc1df1c32295e32980b2a91","image":"https:\/\/fb-cdn.fanbook.mobi\/fanbook\/meishe\/SDKLib\/stickerSource2\/63C46D07-79E9-4E60-AA7D-AABADB78F1BC.png","name":"像素礼盒","zip":"https:\/\/fb-cdn.fanbook.mobi\/fanbook\/meishe\/SDKLib\/stickerSource2\/63C46D07-79E9-4E60-AA7D-AABADB78F1BC.zip","lic":"https:\/\/fb-cdn.fanbook.mobi\/fanbook\/meishe\/SDKLib\/sticker\/68-像素礼盒\/63C46D07-79E9-4E60-AA7D-AABADB78F1BC.lic"},{"fileName":"7732C11A-D0F6-4A68-ACFF-65F7CCEFB225.2.animatedsticker","url":"https:\/\/fb-cdn.fanbook.mobi\/fanbook\/meishe\/SDKLib\/stickerSource2\/7732C11A-D0F6-4A68-ACFF-65F7CCEFB225.2.animatedsticker","strong":0,"md5":"8664c3bb26c166ce527ccf78cebbf05e","image":"https:\/\/fb-cdn.fanbook.mobi\/fanbook\/meishe\/SDKLib\/stickerSource2\/7732C11A-D0F6-4A68-ACFF-65F7CCEFB225.webp","name":"大白鹅","zip":"https:\/\/fb-cdn.fanbook.mobi\/fanbook\/meishe\/SDKLib\/stickerSource2\/7732C11A-D0F6-4A68-ACFF-65F7CCEFB225.zip","lic":"https:\/\/fb-cdn.fanbook.mobi\/fanbook\/meishe\/SDKLib\/sticker\/69-大白鹅\/7732C11A-D0F6-4A68-ACFF-65F7CCEFB225.lic"},{"fileName":"6E4D5762-9256-4ADD-9A32-77FDF7627C44.2.animatedsticker","url":"https:\/\/fb-cdn.fanbook.mobi\/fanbook\/meishe\/SDKLib\/stickerSource2\/6E4D5762-9256-4ADD-9A32-77FDF7627C44.2.animatedsticker","strong":0,"md5":"e73390ea64f55baf03d2eac27fc8b34c","image":"https:\/\/fb-cdn.fanbook.mobi\/fanbook\/meishe\/SDKLib\/stickerSource2\/6E4D5762-9256-4ADD-9A32-77FDF7627C44.webp","name":"小黄鸭","zip":"https:\/\/fb-cdn.fanbook.mobi\/fanbook\/meishe\/SDKLib\/stickerSource2\/6E4D5762-9256-4ADD-9A32-77FDF7627C44.zip","lic":"https:\/\/fb-cdn.fanbook.mobi\/fanbook\/meishe\/SDKLib\/sticker\/70-小黄鸭\/6E4D5762-9256-4ADD-9A32-77FDF7627C44.lic"},{"fileName":"7375E1BA-909B-4524-8EFF-33FABB055E4D.1.animatedsticker","url":"https:\/\/fb-cdn.fanbook.mobi\/fanbook\/meishe\/SDKLib\/stickerSource2\/7375E1BA-909B-4524-8EFF-33FABB055E4D.1.animatedsticker","strong":0,"md5":"6e6913d03abcff97ff2c7943e1a93929","image":"https:\/\/fb-cdn.fanbook.mobi\/fanbook\/meishe\/SDKLib\/stickerSource2\/7375E1BA-909B-4524-8EFF-33FABB055E4D.png","name":"西瓜","zip":"https:\/\/fb-cdn.fanbook.mobi\/fanbook\/meishe\/SDKLib\/stickerSource2\/7375E1BA-909B-4524-8EFF-33FABB055E4D.zip","lic":"https:\/\/fb-cdn.fanbook.mobi\/fanbook\/meishe\/SDKLib\/sticker\/71-西瓜\/7375E1BA-909B-4524-8EFF-33FABB055E4D.lic"},{"fileName":"9F7F9D5B-B4C0-410E-B54F-FBDECFDA6CBF.1.animatedsticker","url":"https:\/\/fb-cdn.fanbook.mobi\/fanbook\/meishe\/SDKLib\/stickerSource2\/9F7F9D5B-B4C0-410E-B54F-FBDECFDA6CBF.1.animatedsticker","strong":0,"md5":"dd625d6a5bbdb4f0740d5ab18343ad3d","image":"https:\/\/fb-cdn.fanbook.mobi\/fanbook\/meishe\/SDKLib\/stickerSource2\/9F7F9D5B-B4C0-410E-B54F-FBDECFDA6CBF.png","name":"彩虹","zip":"https:\/\/fb-cdn.fanbook.mobi\/fanbook\/meishe\/SDKLib\/stickerSource2\/9F7F9D5B-B4C0-410E-B54F-FBDECFDA6CBF.zip","lic":"https:\/\/fb-cdn.fanbook.mobi\/fanbook\/meishe\/SDKLib\/sticker\/72-彩虹\/9F7F9D5B-B4C0-410E-B54F-FBDECFDA6CBF.lic"},{"fileName":"DCE7B659-78EF-4DD2-B4F4-238298427278.1.animatedsticker","url":"https:\/\/fb-cdn.fanbook.mobi\/fanbook\/meishe\/SDKLib\/stickerSource2\/DCE7B659-78EF-4DD2-B4F4-238298427278.1.animatedsticker","strong":0,"md5":"0412879e87cac9cd1bfaee44736915f5","image":"https:\/\/fb-cdn.fanbook.mobi\/fanbook\/meishe\/SDKLib\/stickerSource2\/DCE7B659-78EF-4DD2-B4F4-238298427278.png","name":"太阳","zip":"https:\/\/fb-cdn.fanbook.mobi\/fanbook\/meishe\/SDKLib\/stickerSource2\/DCE7B659-78EF-4DD2-B4F4-238298427278.zip","lic":"https:\/\/fb-cdn.fanbook.mobi\/fanbook\/meishe\/SDKLib\/sticker\/73-太阳\/DCE7B659-78EF-4DD2-B4F4-238298427278.lic"}],"filterArray":[{"fileName":"DB444A3D-647C-4C0A-BED3-7EBF97801F98.1.videofx","url":"https:\/\/fb-cdn.fanbook.mobi\/fanbook\/meishe\/SDKLib\/fliterSource2\/DB444A3D-647C-4C0A-BED3-7EBF97801F98.1.videofx","strong":80,"md5":"6db30d5a2ca14a1c24d65773381bea30","image":"https:\/\/fb-cdn.fanbook.mobi\/fanbook\/meishe\/SDKLib\/fliterSource2\/DB444A3D-647C-4C0A-BED3-7EBF97801F98.png","name":"清新","zip":"https:\/\/fb-cdn.fanbook.mobi\/fanbook\/meishe\/SDKLib\/fliterSource2\/DB444A3D-647C-4C0A-BED3-7EBF97801F98.zip","lic":"https:\/\/fb-cdn.fanbook.mobi\/fanbook\/meishe\/SDKLib\/fliter\/1-清新-80\/DB444A3D-647C-4C0A-BED3-7EBF97801F98.lic"},{"fileName":"2E50789E-C55E-4506-BDCB-DB5F105823A0.2.videofx","url":"https:\/\/fb-cdn.fanbook.mobi\/fanbook\/meishe\/SDKLib\/fliterSource2\/2E50789E-C55E-4506-BDCB-DB5F105823A0.2.videofx","strong":80,"md5":"7d7a8f08e9fc3faf9333eea8ad8be93e","image":"https:\/\/fb-cdn.fanbook.mobi\/fanbook\/meishe\/SDKLib\/fliterSource2\/2E50789E-C55E-4506-BDCB-DB5F105823A0.png","name":"少女","zip":"https:\/\/fb-cdn.fanbook.mobi\/fanbook\/meishe\/SDKLib\/fliterSource2\/2E50789E-C55E-4506-BDCB-DB5F105823A0.zip","lic":"https:\/\/fb-cdn.fanbook.mobi\/fanbook\/meishe\/SDKLib\/fliter\/2-少女-80\/2E50789E-C55E-4506-BDCB-DB5F105823A0.lic"},{"fileName":"D1C01CF7-CA73-4CB7-A6B7-630B5FF9EC74.1.videofx","url":"https:\/\/fb-cdn.fanbook.mobi\/fanbook\/meishe\/SDKLib\/fliterSource2\/D1C01CF7-CA73-4CB7-A6B7-630B5FF9EC74.1.videofx","strong":80,"md5":"b815e4a0956008a51a46d7a5cb8967bf","image":"https:\/\/fb-cdn.fanbook.mobi\/fanbook\/meishe\/SDKLib\/fliterSource2\/D1C01CF7-CA73-4CB7-A6B7-630B5FF9EC74.png","name":"自然","zip":"https:\/\/fb-cdn.fanbook.mobi\/fanbook\/meishe\/SDKLib\/fliterSource2\/D1C01CF7-CA73-4CB7-A6B7-630B5FF9EC74.zip","lic":"https:\/\/fb-cdn.fanbook.mobi\/fanbook\/meishe\/SDKLib\/fliter\/3-自然-80\/D1C01CF7-CA73-4CB7-A6B7-630B5FF9EC74.lic"},{"fileName":"647136C2-D334-4FFC-8949-36F2B3CC94DC.2.videofx","url":"https:\/\/fb-cdn.fanbook.mobi\/fanbook\/meishe\/SDKLib\/fliterSource2\/647136C2-D334-4FFC-8949-36F2B3CC94DC.2.videofx","strong":80,"md5":"ddef7f54bb8451b4b2085c3137cb2eb5","image":"https:\/\/fb-cdn.fanbook.mobi\/fanbook\/meishe\/SDKLib\/fliterSource2\/647136C2-D334-4FFC-8949-36F2B3CC94DC.png","name":"水雾","zip":"https:\/\/fb-cdn.fanbook.mobi\/fanbook\/meishe\/SDKLib\/fliterSource2\/647136C2-D334-4FFC-8949-36F2B3CC94DC.zip","lic":"https:\/\/fb-cdn.fanbook.mobi\/fanbook\/meishe\/SDKLib\/fliter\/4-水雾-80\/647136C2-D334-4FFC-8949-36F2B3CC94DC.lic"},{"fileName":"C875A72D-F184-4386-9030-5C02C7B98C31.1.videofx","url":"https:\/\/fb-cdn.fanbook.mobi\/fanbook\/meishe\/SDKLib\/fliterSource2\/C875A72D-F184-4386-9030-5C02C7B98C31.1.videofx","strong":80,"md5":"ed95d49070744d78bf27dd1150824650","image":"https:\/\/fb-cdn.fanbook.mobi\/fanbook\/meishe\/SDKLib\/fliterSource2\/C875A72D-F184-4386-9030-5C02C7B98C31.png","name":"粉夏","zip":"https:\/\/fb-cdn.fanbook.mobi\/fanbook\/meishe\/SDKLib\/fliterSource2\/C875A72D-F184-4386-9030-5C02C7B98C31.zip","lic":"https:\/\/fb-cdn.fanbook.mobi\/fanbook\/meishe\/SDKLib\/fliter\/5-粉夏-80\/C875A72D-F184-4386-9030-5C02C7B98C31.lic"},{"fileName":"576814FB-A479-46AB-A58D-017A1865FC14.2.videofx","url":"https:\/\/fb-cdn.fanbook.mobi\/fanbook\/meishe\/SDKLib\/fliterSource2\/576814FB-A479-46AB-A58D-017A1865FC14.2.videofx","strong":80,"md5":"21086addd29e4bab1d38e88e63071d5c","image":"https:\/\/fb-cdn.fanbook.mobi\/fanbook\/meishe\/SDKLib\/fliterSource2\/576814FB-A479-46AB-A58D-017A1865FC14.png","name":"御姐","zip":"https:\/\/fb-cdn.fanbook.mobi\/fanbook\/meishe\/SDKLib\/fliterSource2\/576814FB-A479-46AB-A58D-017A1865FC14.zip","lic":"https:\/\/fb-cdn.fanbook.mobi\/fanbook\/meishe\/SDKLib\/fliter\/6-御姐-80\/576814FB-A479-46AB-A58D-017A1865FC14.lic"},{"fileName":"F940B90D-A5D7-4823-BBD6-397EDDE765CF.1.videofx","url":"https:\/\/fb-cdn.fanbook.mobi\/fanbook\/meishe\/SDKLib\/fliterSource2\/F940B90D-A5D7-4823-BBD6-397EDDE765CF.1.videofx","strong":80,"md5":"b51df14671229b3c3f5e504101775614","image":"https:\/\/fb-cdn.fanbook.mobi\/fanbook\/meishe\/SDKLib\/fliterSource2\/F940B90D-A5D7-4823-BBD6-397EDDE765CF.png","name":"轻胶","zip":"https:\/\/fb-cdn.fanbook.mobi\/fanbook\/meishe\/SDKLib\/fliterSource2\/F940B90D-A5D7-4823-BBD6-397EDDE765CF.zip","lic":"https:\/\/fb-cdn.fanbook.mobi\/fanbook\/meishe\/SDKLib\/fliter\/7-轻胶-80\/F940B90D-A5D7-4823-BBD6-397EDDE765CF.lic"},{"fileName":"D7CF1C93-DF2C-419B-A36A-A79749AEB0A5.1.videofx","url":"https:\/\/fb-cdn.fanbook.mobi\/fanbook\/meishe\/SDKLib\/fliterSource2\/D7CF1C93-DF2C-419B-A36A-A79749AEB0A5.1.videofx","strong":80,"md5":"9fcab7686317f223993acd0000fddbb3","image":"https:\/\/fb-cdn.fanbook.mobi\/fanbook\/meishe\/SDKLib\/fliterSource2\/D7CF1C93-DF2C-419B-A36A-A79749AEB0A5.png","name":"文艺","zip":"https:\/\/fb-cdn.fanbook.mobi\/fanbook\/meishe\/SDKLib\/fliterSource2\/D7CF1C93-DF2C-419B-A36A-A79749AEB0A5.zip","lic":"https:\/\/fb-cdn.fanbook.mobi\/fanbook\/meishe\/SDKLib\/fliter\/8-文艺-80\/D7CF1C93-DF2C-419B-A36A-A79749AEB0A5.lic"},{"fileName":"707901CB-0234-48DE-9719-3ABE45C18104.1.videofx","url":"https:\/\/fb-cdn.fanbook.mobi\/fanbook\/meishe\/SDKLib\/fliterSource2\/707901CB-0234-48DE-9719-3ABE45C18104.1.videofx","strong":80,"md5":"f7f063e7858bf39807f7883cfb654fc2","image":"https:\/\/fb-cdn.fanbook.mobi\/fanbook\/meishe\/SDKLib\/fliterSource2\/707901CB-0234-48DE-9719-3ABE45C18104.png","name":"复古","zip":"https:\/\/fb-cdn.fanbook.mobi\/fanbook\/meishe\/SDKLib\/fliterSource2\/707901CB-0234-48DE-9719-3ABE45C18104.zip","lic":"https:\/\/fb-cdn.fanbook.mobi\/fanbook\/meishe\/SDKLib\/fliter\/9-复古-80\/707901CB-0234-48DE-9719-3ABE45C18104.lic"},{"fileName":"E8D602E2-165B-4FE0-96C8-07B24C411A1B.1.videofx","url":"https:\/\/fb-cdn.fanbook.mobi\/fanbook\/meishe\/SDKLib\/fliterSource2\/E8D602E2-165B-4FE0-96C8-07B24C411A1B.1.videofx","strong":80,"md5":"0bfe523adbfa8f646b613a1516201ed5","image":"https:\/\/fb-cdn.fanbook.mobi\/fanbook\/meishe\/SDKLib\/fliterSource2\/E8D602E2-165B-4FE0-96C8-07B24C411A1B.png","name":"摩卡","zip":"https:\/\/fb-cdn.fanbook.mobi\/fanbook\/meishe\/SDKLib\/fliterSource2\/E8D602E2-165B-4FE0-96C8-07B24C411A1B.zip","lic":"https:\/\/fb-cdn.fanbook.mobi\/fanbook\/meishe\/SDKLib\/fliter\/10-摩卡-80\/E8D602E2-165B-4FE0-96C8-07B24C411A1B.lic"},{"fileName":"300C2A7B-411E-441C-BDB0-A5CF7560D0E2.1.videofx","url":"https:\/\/fb-cdn.fanbook.mobi\/fanbook\/meishe\/SDKLib\/fliterSource2\/300C2A7B-411E-441C-BDB0-A5CF7560D0E2.1.videofx","strong":80,"md5":"30505e21d42b509ddfff6f662c45d162","image":"https:\/\/fb-cdn.fanbook.mobi\/fanbook\/meishe\/SDKLib\/fliterSource2\/300C2A7B-411E-441C-BDB0-A5CF7560D0E2.png","name":"浪漫","zip":"https:\/\/fb-cdn.fanbook.mobi\/fanbook\/meishe\/SDKLib\/fliterSource2\/300C2A7B-411E-441C-BDB0-A5CF7560D0E2.zip","lic":"https:\/\/fb-cdn.fanbook.mobi\/fanbook\/meishe\/SDKLib\/fliter\/11-浪漫-80\/300C2A7B-411E-441C-BDB0-A5CF7560D0E2.lic"},{"fileName":"73844D15-405B-4B3F-AC71-403B7E069166.1.videofx","url":"https:\/\/fb-cdn.fanbook.mobi\/fanbook\/meishe\/SDKLib\/fliterSource2\/73844D15-405B-4B3F-AC71-403B7E069166.1.videofx","strong":90,"md5":"8330519b40cf3a6c01ca6742402b877d","image":"https:\/\/fb-cdn.fanbook.mobi\/fanbook\/meishe\/SDKLib\/fliterSource2\/73844D15-405B-4B3F-AC71-403B7E069166.png","name":"杂志","zip":"https:\/\/fb-cdn.fanbook.mobi\/fanbook\/meishe\/SDKLib\/fliterSource2\/73844D15-405B-4B3F-AC71-403B7E069166.zip","lic":"https:\/\/fb-cdn.fanbook.mobi\/fanbook\/meishe\/SDKLib\/fliter\/12-杂志-90\/73844D15-405B-4B3F-AC71-403B7E069166.lic"},{"fileName":"D9E6D8CA-5824-420B-A713-BF9908EE53A9.1.videofx","url":"https:\/\/fb-cdn.fanbook.mobi\/fanbook\/meishe\/SDKLib\/fliterSource2\/D9E6D8CA-5824-420B-A713-BF9908EE53A9.1.videofx","strong":80,"md5":"d943a5ff0166bca034778abb33461be4","image":"https:\/\/fb-cdn.fanbook.mobi\/fanbook\/meishe\/SDKLib\/fliterSource2\/D9E6D8CA-5824-420B-A713-BF9908EE53A9.png","name":"黄昏","zip":"https:\/\/fb-cdn.fanbook.mobi\/fanbook\/meishe\/SDKLib\/fliterSource2\/D9E6D8CA-5824-420B-A713-BF9908EE53A9.zip","lic":"https:\/\/fb-cdn.fanbook.mobi\/fanbook\/meishe\/SDKLib\/fliter\/13-黄昏-80\/D9E6D8CA-5824-420B-A713-BF9908EE53A9.lic"},{"fileName":"C069F79D-F8DA-459A-8239-D25E8A304976.1.videofx","url":"https:\/\/fb-cdn.fanbook.mobi\/fanbook\/meishe\/SDKLib\/fliterSource2\/C069F79D-F8DA-459A-8239-D25E8A304976.1.videofx","strong":80,"md5":"8b2f497dc2bcec006d285c38f7a51479","image":"https:\/\/fb-cdn.fanbook.mobi\/fanbook\/meishe\/SDKLib\/fliterSource2\/C069F79D-F8DA-459A-8239-D25E8A304976.png","name":"明亮","zip":"https:\/\/fb-cdn.fanbook.mobi\/fanbook\/meishe\/SDKLib\/fliterSource2\/C069F79D-F8DA-459A-8239-D25E8A304976.zip","lic":"https:\/\/fb-cdn.fanbook.mobi\/fanbook\/meishe\/SDKLib\/fliter\/14-明亮-80\/C069F79D-F8DA-459A-8239-D25E8A304976.lic"},{"fileName":"0FD9D336-07C2-4CAA-BCE2-85F01367AF03.1.videofx","url":"https:\/\/fb-cdn.fanbook.mobi\/fanbook\/meishe\/SDKLib\/fliterSource2\/0FD9D336-07C2-4CAA-BCE2-85F01367AF03.1.videofx","strong":80,"md5":"75cdba801a57c76adb048f4b276ab67c","image":"https:\/\/fb-cdn.fanbook.mobi\/fanbook\/meishe\/SDKLib\/fliterSource2\/0FD9D336-07C2-4CAA-BCE2-85F01367AF03.png","name":"时光","zip":"https:\/\/fb-cdn.fanbook.mobi\/fanbook\/meishe\/SDKLib\/fliterSource2\/0FD9D336-07C2-4CAA-BCE2-85F01367AF03.zip","lic":"https:\/\/fb-cdn.fanbook.mobi\/fanbook\/meishe\/SDKLib\/fliter\/15-时光-80\/0FD9D336-07C2-4CAA-BCE2-85F01367AF03.lic"},{"fileName":"9FBB0802-E420-4AEB-BA06-2CBB1E775F7F.2.videofx","url":"https:\/\/fb-cdn.fanbook.mobi\/fanbook\/meishe\/SDKLib\/fliterSource2\/9FBB0802-E420-4AEB-BA06-2CBB1E775F7F.2.videofx","strong":80,"md5":"36a9bb1e60dfe28bad2c74679fd37249","image":"https:\/\/fb-cdn.fanbook.mobi\/fanbook\/meishe\/SDKLib\/fliterSource2\/9FBB0802-E420-4AEB-BA06-2CBB1E775F7F.png","name":"过往","zip":"https:\/\/fb-cdn.fanbook.mobi\/fanbook\/meishe\/SDKLib\/fliterSource2\/9FBB0802-E420-4AEB-BA06-2CBB1E775F7F.zip","lic":"https:\/\/fb-cdn.fanbook.mobi\/fanbook\/meishe\/SDKLib\/fliter\/16-过往-80\/9FBB0802-E420-4AEB-BA06-2CBB1E775F7F.lic"},{"fileName":"99DB1822-8368-418E-B685-EE0360A9A65B.1.videofx","url":"https:\/\/fb-cdn.fanbook.mobi\/fanbook\/meishe\/SDKLib\/fliterSource2\/99DB1822-8368-418E-B685-EE0360A9A65B.1.videofx","strong":80,"md5":"2784bfa61e5848e8e14ae13a1dd4dc0f","image":"https:\/\/fb-cdn.fanbook.mobi\/fanbook\/meishe\/SDKLib\/fliterSource2\/99DB1822-8368-418E-B685-EE0360A9A65B.png","name":"仲夏","zip":"https:\/\/fb-cdn.fanbook.mobi\/fanbook\/meishe\/SDKLib\/fliterSource2\/99DB1822-8368-418E-B685-EE0360A9A65B.zip","lic":"https:\/\/fb-cdn.fanbook.mobi\/fanbook\/meishe\/SDKLib\/fliter\/17-仲夏-80\/99DB1822-8368-418E-B685-EE0360A9A65B.lic"},{"fileName":"BC04A0A5-72A3-4BFB-AF34-62A2410E5847.1.videofx","url":"https:\/\/fb-cdn.fanbook.mobi\/fanbook\/meishe\/SDKLib\/fliterSource2\/BC04A0A5-72A3-4BFB-AF34-62A2410E5847.1.videofx","strong":80,"md5":"8ef6dc6c9563b37d67f583d4dd0a3e9a","image":"https:\/\/fb-cdn.fanbook.mobi\/fanbook\/meishe\/SDKLib\/fliterSource2\/BC04A0A5-72A3-4BFB-AF34-62A2410E5847.png","name":"暖秋","zip":"https:\/\/fb-cdn.fanbook.mobi\/fanbook\/meishe\/SDKLib\/fliterSource2\/BC04A0A5-72A3-4BFB-AF34-62A2410E5847.zip","lic":"https:\/\/fb-cdn.fanbook.mobi\/fanbook\/meishe\/SDKLib\/fliter\/18-暖秋-80\/BC04A0A5-72A3-4BFB-AF34-62A2410E5847.lic"},{"fileName":"98E1A508-3506-4C23-A3AD-30E3F2B63FF7.1.videofx","url":"https:\/\/fb-cdn.fanbook.mobi\/fanbook\/meishe\/SDKLib\/fliterSource2\/98E1A508-3506-4C23-A3AD-30E3F2B63FF7.1.videofx","strong":80,"md5":"8b3001e6678b6d2d633fd0c9ed2baa95","image":"https:\/\/fb-cdn.fanbook.mobi\/fanbook\/meishe\/SDKLib\/fliterSource2\/98E1A508-3506-4C23-A3AD-30E3F2B63FF7.png","name":"美味","zip":"https:\/\/fb-cdn.fanbook.mobi\/fanbook\/meishe\/SDKLib\/fliterSource2\/98E1A508-3506-4C23-A3AD-30E3F2B63FF7.zip","lic":"https:\/\/fb-cdn.fanbook.mobi\/fanbook\/meishe\/SDKLib\/fliter\/19-美味-80\/98E1A508-3506-4C23-A3AD-30E3F2B63FF7.lic"},{"fileName":"188B64F2-9D27-425B-ABF5-A1B0EE1BBBCB.1.videofx","url":"https:\/\/fb-cdn.fanbook.mobi\/fanbook\/meishe\/SDKLib\/fliterSource2\/188B64F2-9D27-425B-ABF5-A1B0EE1BBBCB.1.videofx","strong":80,"md5":"d6da3b677d91b52e793d7a58b4b8aa5c","image":"https:\/\/fb-cdn.fanbook.mobi\/fanbook\/meishe\/SDKLib\/fliterSource2\/188B64F2-9D27-425B-ABF5-A1B0EE1BBBCB.png","name":"甜品","zip":"https:\/\/fb-cdn.fanbook.mobi\/fanbook\/meishe\/SDKLib\/fliterSource2\/188B64F2-9D27-425B-ABF5-A1B0EE1BBBCB.zip","lic":"https:\/\/fb-cdn.fanbook.mobi\/fanbook\/meishe\/SDKLib\/fliter\/20-甜品-80\/188B64F2-9D27-425B-ABF5-A1B0EE1BBBCB.lic"},{"fileName":"61B3A8B9-C843-450D-AB93-56FF082FF120.1.videofx","url":"https:\/\/fb-cdn.fanbook.mobi\/fanbook\/meishe\/SDKLib\/fliterSource2\/61B3A8B9-C843-450D-AB93-56FF082FF120.1.videofx","strong":80,"md5":"fcde03542c5540cc2dba4def898fe5f9","image":"https:\/\/fb-cdn.fanbook.mobi\/fanbook\/meishe\/SDKLib\/fliterSource2\/61B3A8B9-C843-450D-AB93-56FF082FF120.png","name":"鲜艳","zip":"https:\/\/fb-cdn.fanbook.mobi\/fanbook\/meishe\/SDKLib\/fliterSource2\/61B3A8B9-C843-450D-AB93-56FF082FF120.zip","lic":"https:\/\/fb-cdn.fanbook.mobi\/fanbook\/meishe\/SDKLib\/fliter\/21-鲜艳-80\/61B3A8B9-C843-450D-AB93-56FF082FF120.lic"},{"fileName":"02B33530-8663-4A01-A6F1-C9DAB3322590.6.videofx","url":"https:\/\/fb-cdn.fanbook.mobi\/fanbook\/meishe\/SDKLib\/fliterSource2\/02B33530-8663-4A01-A6F1-C9DAB3322590.6.videofx","strong":80,"md5":"a1021801235932939f27ddad9a09d7a1","image":"https:\/\/fb-cdn.fanbook.mobi\/fanbook\/meishe\/SDKLib\/fliterSource2\/02B33530-8663-4A01-A6F1-C9DAB3322590.png","name":"焦糖","zip":"https:\/\/fb-cdn.fanbook.mobi\/fanbook\/meishe\/SDKLib\/fliterSource2\/02B33530-8663-4A01-A6F1-C9DAB3322590.zip","lic":"https:\/\/fb-cdn.fanbook.mobi\/fanbook\/meishe\/SDKLib\/fliter\/22-焦糖-80\/02B33530-8663-4A01-A6F1-C9DAB3322590.lic"},{"fileName":"83350933-EBA9-4947-A226-BE1DDA953902.2.videofx","url":"https:\/\/fb-cdn.fanbook.mobi\/fanbook\/meishe\/SDKLib\/fliterSource2\/83350933-EBA9-4947-A226-BE1DDA953902.2.videofx","strong":80,"md5":"e436877d04d78c431fd708268dd22614","image":"https:\/\/fb-cdn.fanbook.mobi\/fanbook\/meishe\/SDKLib\/fliterSource2\/83350933-EBA9-4947-A226-BE1DDA953902.png","name":"下午茶","zip":"https:\/\/fb-cdn.fanbook.mobi\/fanbook\/meishe\/SDKLib\/fliterSource2\/83350933-EBA9-4947-A226-BE1DDA953902.zip","lic":"https:\/\/fb-cdn.fanbook.mobi\/fanbook\/meishe\/SDKLib\/fliter\/23-下午茶-80\/83350933-EBA9-4947-A226-BE1DDA953902.lic"},{"fileName":"F592472B-7A07-4F14-B24C-CBE87D5F0F1A.1.videofx","url":"https:\/\/fb-cdn.fanbook.mobi\/fanbook\/meishe\/SDKLib\/fliterSource2\/F592472B-7A07-4F14-B24C-CBE87D5F0F1A.1.videofx","strong":80,"md5":"62b580fe8c15ee5fef5248bee1d4607f","image":"https:\/\/fb-cdn.fanbook.mobi\/fanbook\/meishe\/SDKLib\/fliterSource2\/F592472B-7A07-4F14-B24C-CBE87D5F0F1A.png","name":"胶片","zip":"https:\/\/fb-cdn.fanbook.mobi\/fanbook\/meishe\/SDKLib\/fliterSource2\/F592472B-7A07-4F14-B24C-CBE87D5F0F1A.zip","lic":"https:\/\/fb-cdn.fanbook.mobi\/fanbook\/meishe\/SDKLib\/fliter\/24-胶片-80\/F592472B-7A07-4F14-B24C-CBE87D5F0F1A.lic"},{"fileName":"42C0BAE9-216E-420A-A540-5D1A60C533F0.1.videofx","url":"https:\/\/fb-cdn.fanbook.mobi\/fanbook\/meishe\/SDKLib\/fliterSource2\/42C0BAE9-216E-420A-A540-5D1A60C533F0.1.videofx","strong":100,"md5":"207e32cd7ab368510d0d34604b4c4179","image":"https:\/\/fb-cdn.fanbook.mobi\/fanbook\/meishe\/SDKLib\/fliterSource2\/42C0BAE9-216E-420A-A540-5D1A60C533F0.png","name":"拍立得","zip":"https:\/\/fb-cdn.fanbook.mobi\/fanbook\/meishe\/SDKLib\/fliterSource2\/42C0BAE9-216E-420A-A540-5D1A60C533F0.zip","lic":"https:\/\/fb-cdn.fanbook.mobi\/fanbook\/meishe\/SDKLib\/fliter\/25-拍立得-100\/42C0BAE9-216E-420A-A540-5D1A60C533F0.lic"},{"fileName":"BCD1FAAD-D5C5-468F-A4F2-1C2138F485C0.3.videofx","url":"https:\/\/fb-cdn.fanbook.mobi\/fanbook\/meishe\/SDKLib\/fliterSource2\/BCD1FAAD-D5C5-468F-A4F2-1C2138F485C0.3.videofx","strong":100,"md5":"56f21eb204f18e6d40bd521ebafd894c","image":"https:\/\/fb-cdn.fanbook.mobi\/fanbook\/meishe\/SDKLib\/fliterSource2\/BCD1FAAD-D5C5-468F-A4F2-1C2138F485C0.png","name":"抖动","zip":"https:\/\/fb-cdn.fanbook.mobi\/fanbook\/meishe\/SDKLib\/fliterSource2\/BCD1FAAD-D5C5-468F-A4F2-1C2138F485C0.zip","lic":"https:\/\/fb-cdn.fanbook.mobi\/fanbook\/meishe\/SDKLib\/fliter\/26-抖动-100\/BCD1FAAD-D5C5-468F-A4F2-1C2138F485C0.lic"},{"fileName":"FFC08CC6-6BF0-47C6-9F05-559FDC4CFE4D.1.videofx","url":"https:\/\/fb-cdn.fanbook.mobi\/fanbook\/meishe\/SDKLib\/fliterSource2\/FFC08CC6-6BF0-47C6-9F05-559FDC4CFE4D.1.videofx","strong":100,"md5":"5ac2d8f9604358c0315dbd76e4cb0374","image":"https:\/\/fb-cdn.fanbook.mobi\/fanbook\/meishe\/SDKLib\/fliterSource2\/FFC08CC6-6BF0-47C6-9F05-559FDC4CFE4D.png","name":"赛博","zip":"https:\/\/fb-cdn.fanbook.mobi\/fanbook\/meishe\/SDKLib\/fliterSource2\/FFC08CC6-6BF0-47C6-9F05-559FDC4CFE4D.zip","lic":"https:\/\/fb-cdn.fanbook.mobi\/fanbook\/meishe\/SDKLib\/fliter\/27-赛博-100\/FFC08CC6-6BF0-47C6-9F05-559FDC4CFE4D.lic"},{"fileName":"0785C0D9-12E7-4A3D-9496-6199F9FDDD2C.6.videofx","url":"https:\/\/fb-cdn.fanbook.mobi\/fanbook\/meishe\/SDKLib\/fliterSource2\/0785C0D9-12E7-4A3D-9496-6199F9FDDD2C.6.videofx","strong":100,"md5":"82eb83a49bf2c02a04ddab1a973458d8","image":"https:\/\/fb-cdn.fanbook.mobi\/fanbook\/meishe\/SDKLib\/fliterSource2\/0785C0D9-12E7-4A3D-9496-6199F9FDDD2C.png","name":"取景器","zip":"https:\/\/fb-cdn.fanbook.mobi\/fanbook\/meishe\/SDKLib\/fliterSource2\/0785C0D9-12E7-4A3D-9496-6199F9FDDD2C.zip","lic":"https:\/\/fb-cdn.fanbook.mobi\/fanbook\/meishe\/SDKLib\/fliter\/28-取景器-100\/0785C0D9-12E7-4A3D-9496-6199F9FDDD2C.lic"},{"fileName":"66831999-C84C-4B0A-9554-A97FC075693B.4.videofx","url":"https:\/\/fb-cdn.fanbook.mobi\/fanbook\/meishe\/SDKLib\/fliterSource2\/66831999-C84C-4B0A-9554-A97FC075693B.4.videofx","strong":100,"md5":"ded297e2c6344f5dae97af8ba706f142","image":"https:\/\/fb-cdn.fanbook.mobi\/fanbook\/meishe\/SDKLib\/fliterSource2\/66831999-C84C-4B0A-9554-A97FC075693B.png","name":"色差","zip":"https:\/\/fb-cdn.fanbook.mobi\/fanbook\/meishe\/SDKLib\/fliterSource2\/66831999-C84C-4B0A-9554-A97FC075693B.zip","lic":"https:\/\/fb-cdn.fanbook.mobi\/fanbook\/meishe\/SDKLib\/fliter\/29-色差-100\/66831999-C84C-4B0A-9554-A97FC075693B.lic"},{"fileName":"87AA330F-431B-46AB-9C10-FA0ADEB5604F.4.videofx","url":"https:\/\/fb-cdn.fanbook.mobi\/fanbook\/meishe\/SDKLib\/fliterSource2\/87AA330F-431B-46AB-9C10-FA0ADEB5604F.4.videofx","strong":100,"md5":"bdc34d5859490bf97445d58db667bbc3","image":"https:\/\/fb-cdn.fanbook.mobi\/fanbook\/meishe\/SDKLib\/fliterSource2\/87AA330F-431B-46AB-9C10-FA0ADEB5604F.png","name":"灵魂出窍","zip":"https:\/\/fb-cdn.fanbook.mobi\/fanbook\/meishe\/SDKLib\/fliterSource2\/87AA330F-431B-46AB-9C10-FA0ADEB5604F.zip","lic":"https:\/\/fb-cdn.fanbook.mobi\/fanbook\/meishe\/SDKLib\/fliter\/30-灵魂出窍-100\/87AA330F-431B-46AB-9C10-FA0ADEB5604F.lic"},{"fileName":"9D08DC5A-C303-460D-ADD7-82D85B8325AE.1.videofx","url":"https:\/\/fb-cdn.fanbook.mobi\/fanbook\/meishe\/SDKLib\/fliterSource2\/9D08DC5A-C303-460D-ADD7-82D85B8325AE.1.videofx","strong":100,"md5":"f3e151410d683f01eb6edb226de9a4d3","image":"https:\/\/fb-cdn.fanbook.mobi\/fanbook\/meishe\/SDKLib\/fliterSource2\/9D08DC5A-C303-460D-ADD7-82D85B8325AE.png","name":"复古快拍","zip":"https:\/\/fb-cdn.fanbook.mobi\/fanbook\/meishe\/SDKLib\/fliterSource2\/9D08DC5A-C303-460D-ADD7-82D85B8325AE.zip","lic":"https:\/\/fb-cdn.fanbook.mobi\/fanbook\/meishe\/SDKLib\/fliter\/31-复古快拍-100\/9D08DC5A-C303-460D-ADD7-82D85B8325AE.lic"},{"fileName":"AF8F4470-037D-4DF4-9B61-64C59B5EF8F9.4.videofx","url":"https:\/\/fb-cdn.fanbook.mobi\/fanbook\/meishe\/SDKLib\/fliterSource2\/AF8F4470-037D-4DF4-9B61-64C59B5EF8F9.4.videofx","strong":100,"md5":"4dc69b93733d75b455d461388432cdce","image":"https:\/\/fb-cdn.fanbook.mobi\/fanbook\/meishe\/SDKLib\/fliterSource2\/AF8F4470-037D-4DF4-9B61-64C59B5EF8F9.gif","name":"数字雨","zip":"https:\/\/fb-cdn.fanbook.mobi\/fanbook\/meishe\/SDKLib\/fliterSource2\/AF8F4470-037D-4DF4-9B61-64C59B5EF8F9.zip","lic":"https:\/\/fb-cdn.fanbook.mobi\/fanbook\/meishe\/SDKLib\/fliter\/32-数字雨-100\/AF8F4470-037D-4DF4-9B61-64C59B5EF8F9.lic"}],"musicArray":[{"fileName":"Little_Idea.mp3","url":"https:\/\/fb-cdn.fanbook.mobi\/fanbook\/meishe\/SDKLib\/music\/Little_Idea.mp3","strong":0,"md5":"bf0df2e2bb3e6fee0275f6cc7921069c","image":"https:\/\/fb-cdn.fanbook.mobi\/fanbook\/meishe\/SDKLib\/music\/Little_Idea.jpg","name":"Little Idea"},{"fileName":"Moose.mp3","url":"https:\/\/fb-cdn.fanbook.mobi\/fanbook\/meishe\/SDKLib\/music\/Moose.mp3","strong":0,"md5":"39829a01217684c25f73946bfe136b6f","image":"https:\/\/fb-cdn.fanbook.mobi\/fanbook\/meishe\/SDKLib\/music\/Moose.jpg","name":"Moose"},{"fileName":"Cute.mp3","url":"https:\/\/fb-cdn.fanbook.mobi\/fanbook\/meishe\/SDKLib\/music\/Cute.mp3","strong":0,"md5":"0466433ce33c4df06743075bef864477","image":"https:\/\/fb-cdn.fanbook.mobi\/fanbook\/meishe\/SDKLib\/music\/Cute.jpg","name":"Cute"},{"fileName":"Memories.mp3","url":"https:\/\/fb-cdn.fanbook.mobi\/fanbook\/meishe\/SDKLib\/music\/Memories.mp3","strong":0,"md5":"fa2785d17195b2689a037990151d23a3","image":"https:\/\/fb-cdn.fanbook.mobi\/fanbook\/meishe\/SDKLib\/music\/Memories.jpg","name":"Memories"},{"fileName":"Slow_Motion.mp3","url":"https:\/\/fb-cdn.fanbook.mobi\/fanbook\/meishe\/SDKLib\/music\/Slow_Motion.mp3","strong":0,"md5":"e0e75e5b7f2eaa57ab39b3a6e5a40f0b","image":"https:\/\/fb-cdn.fanbook.mobi\/fanbook\/meishe\/SDKLib\/music\/Slow_Motion.jpg","name":"Slow Motion"},{"fileName":"Tomorrow.mp3","url":"https:\/\/fb-cdn.fanbook.mobi\/fanbook\/meishe\/SDKLib\/music\/Tomorrow.mp3","strong":0,"md5":"63cc0a849da3671271a9ccfb7c335d54","image":"https:\/\/fb-cdn.fanbook.mobi\/fanbook\/meishe\/SDKLib\/music\/Tomorrow.jpg","name":"Tomorrow"},{"fileName":"Sweet.mp3","url":"https:\/\/fb-cdn.fanbook.mobi\/fanbook\/meishe\/SDKLib\/music\/Sweet.mp3","strong":0,"md5":"783e4bf46af5074e1e27dac3398e6ae5","image":"https:\/\/fb-cdn.fanbook.mobi\/fanbook\/meishe\/SDKLib\/music\/Sweet.jpg","name":"Sweet"},{"fileName":"Once_Again.mp3","url":"https:\/\/fb-cdn.fanbook.mobi\/fanbook\/meishe\/SDKLib\/music\/Once_Again.mp3","strong":0,"md5":"b7303a025fee4c52c32f735833b2bbfa","image":"https:\/\/fb-cdn.fanbook.mobi\/fanbook\/meishe\/SDKLib\/music\/Once_Again.jpg","name":"Once Again"},{"fileName":"Going_Higher.mp3","url":"https:\/\/fb-cdn.fanbook.mobi\/fanbook\/meishe\/SDKLib\/music\/Going_Higher.mp3","strong":0,"md5":"2057ee6b687b56fb853af3b3574711cf","image":"https:\/\/fb-cdn.fanbook.mobi\/fanbook\/meishe\/SDKLib\/music\/Going_Higher.jpg","name":"Going Higher"},{"fileName":"A_New_Beginning.mp3","url":"https:\/\/fb-cdn.fanbook.mobi\/fanbook\/meishe\/SDKLib\/music\/A_New_Beginning.mp3","strong":0,"md5":"8d647f68d81408dde5c4e1ed7dfb8527","image":"https:\/\/fb-cdn.fanbook.mobi\/fanbook\/meishe\/SDKLib\/music\/A_New_Beginning.jpg","name":"A New Beginning"},{"fileName":"Energy.mp3","url":"https:\/\/fb-cdn.fanbook.mobi\/fanbook\/meishe\/SDKLib\/music\/Energy.mp3","strong":0,"md5":"78d8e9ad461f0f452cfd9104624cd2d2","image":"https:\/\/fb-cdn.fanbook.mobi\/fanbook\/meishe\/SDKLib\/music\/Energy.jpg","name":"Energy"},{"fileName":"Adventure.mp3","url":"https:\/\/fb-cdn.fanbook.mobi\/fanbook\/meishe\/SDKLib\/music\/Adventure.mp3","strong":0,"md5":"d470b79f97de680743b51915f6dd788b","image":"https:\/\/fb-cdn.fanbook.mobi\/fanbook\/meishe\/SDKLib\/music\/Adventure.jpg","name":"Adventure"},{"fileName":"Evolution.mp3","url":"https:\/\/fb-cdn.fanbook.mobi\/fanbook\/meishe\/SDKLib\/music\/Evolution.mp3","strong":0,"md5":"af3504162fc7eaed46e2bbd70cf3c92a","image":"https:\/\/fb-cdn.fanbook.mobi\/fanbook\/meishe\/SDKLib\/music\/Evolution.jpg","name":"Evolution"},{"fileName":"Ukulele.mp3","url":"https:\/\/fb-cdn.fanbook.mobi\/fanbook\/meishe\/SDKLib\/music\/Ukulele.mp3","strong":0,"md5":"9569869286a4e88efa8724d24f50bf47","image":"https:\/\/fb-cdn.fanbook.mobi\/fanbook\/meishe\/SDKLib\/music\/Ukulele.jpg","name":"Ukulele"},{"fileName":"Summer.mp3","url":"https:\/\/fb-cdn.fanbook.mobi\/fanbook\/meishe\/SDKLib\/music\/Summer.mp3","strong":0,"md5":"fd79b1142f66f1981d0aea1a0b1501ea","image":"https:\/\/fb-cdn.fanbook.mobi\/fanbook\/meishe\/SDKLib\/music\/Summer.jpg","name":"Summer"},{"fileName":"E_R_F.mp3","url":"https:\/\/fb-cdn.fanbook.mobi\/fanbook\/meishe\/SDKLib\/music\/E_R_F.mp3","strong":0,"md5":"d19f8a6e6c112e9ef94be2be1beae47c","image":"https:\/\/fb-cdn.fanbook.mobi\/fanbook\/meishe\/SDKLib\/music\/E_R_F.jpg","name":"E R F"}]}
